{
"meta":{"test_sets":[],"test_metrics":[],"learn_metrics":[{"best_value":"Min","name":"Logloss"}],"launch_mode":"Train","parameters":"","iteration_count":1000,"learn_sets":["learn"],"name":"experiment"},
"iterations":[
{"learn":[0.6629369708],"iteration":0,"passed_time":0.06395705403,"remaining_time":63.89309698},
{"learn":[0.6339061115],"iteration":1,"passed_time":0.07899623323,"remaining_time":39.41912038},
{"learn":[0.6098035861],"iteration":2,"passed_time":0.09381303493,"remaining_time":31.17719861},
{"learn":[0.5867016205],"iteration":3,"passed_time":0.1088727494,"remaining_time":27.1093146},
{"learn":[0.5651251287],"iteration":4,"passed_time":0.1241945932,"remaining_time":24.71472405},
{"learn":[0.5432949062],"iteration":5,"passed_time":0.1391381591,"remaining_time":23.05055502},
{"learn":[0.5231863442],"iteration":6,"passed_time":0.1542899553,"remaining_time":21.88713224},
{"learn":[0.5038684447],"iteration":7,"passed_time":0.168534064,"remaining_time":20.89822394},
{"learn":[0.4851699081],"iteration":8,"passed_time":0.179475698,"remaining_time":19.76226852},
{"learn":[0.4701795461],"iteration":9,"passed_time":0.1894720259,"remaining_time":18.75773057},
{"learn":[0.4542503005],"iteration":10,"passed_time":0.1992549292,"remaining_time":17.91482955},
{"learn":[0.4385262331],"iteration":11,"passed_time":0.2068920139,"remaining_time":17.03410914},
{"learn":[0.4256785552],"iteration":12,"passed_time":0.2132621836,"remaining_time":16.19152117},
{"learn":[0.4138520997],"iteration":13,"passed_time":0.2195442404,"remaining_time":15.46218722},
{"learn":[0.4015892506],"iteration":14,"passed_time":0.2302760567,"remaining_time":15.12146105},
{"learn":[0.3919542192],"iteration":15,"passed_time":0.2349464004,"remaining_time":14.44920362},
{"learn":[0.382653497],"iteration":16,"passed_time":0.2394449666,"remaining_time":13.84555307},
{"learn":[0.3723890945],"iteration":17,"passed_time":0.2440129454,"remaining_time":13.3122618},
{"learn":[0.3634058469],"iteration":18,"passed_time":0.2479996973,"remaining_time":12.80461595},
{"learn":[0.3560364816],"iteration":19,"passed_time":0.2519259202,"remaining_time":12.34437009},
{"learn":[0.3485114049],"iteration":20,"passed_time":0.2557843123,"remaining_time":11.92442104},
{"learn":[0.3404426266],"iteration":21,"passed_time":0.2597316238,"remaining_time":11.54625127},
{"learn":[0.3338137158],"iteration":22,"passed_time":0.2634600776,"remaining_time":11.1913259},
{"learn":[0.3277035912],"iteration":23,"passed_time":0.2674335843,"remaining_time":10.87563243},
{"learn":[0.3213445751],"iteration":24,"passed_time":0.2714667476,"remaining_time":10.58720316},
{"learn":[0.3153947394],"iteration":25,"passed_time":0.2753100518,"remaining_time":10.31353809},
{"learn":[0.3097478483],"iteration":26,"passed_time":0.2791787371,"remaining_time":10.06077449},
{"learn":[0.304392862],"iteration":27,"passed_time":0.2830766773,"remaining_time":9.826804656},
{"learn":[0.3000061901],"iteration":28,"passed_time":0.287280588,"remaining_time":9.618946585},
{"learn":[0.2954169269],"iteration":29,"passed_time":0.2913202915,"remaining_time":9.419356093},
{"learn":[0.2904328058],"iteration":30,"passed_time":0.2950995452,"remaining_time":9.224240622},
{"learn":[0.2863055692],"iteration":31,"passed_time":0.2987850625,"remaining_time":9.038248141},
{"learn":[0.282858969],"iteration":32,"passed_time":0.3025745527,"remaining_time":8.866351287},
{"learn":[0.2795902397],"iteration":33,"passed_time":0.3064376668,"remaining_time":8.706434886},
{"learn":[0.2756006168],"iteration":34,"passed_time":0.3101682391,"remaining_time":8.551781449},
{"learn":[0.2720246478],"iteration":35,"passed_time":0.3138498031,"remaining_time":8.404200284},
{"learn":[0.2692728224],"iteration":36,"passed_time":0.3179662558,"remaining_time":8.275716334},
{"learn":[0.2654406509],"iteration":37,"passed_time":0.3226349556,"remaining_time":8.167758613},
{"learn":[0.2624370975],"iteration":38,"passed_time":0.3277958502,"remaining_time":8.07722595},
{"learn":[0.2601880614],"iteration":39,"passed_time":0.3325404134,"remaining_time":7.980969921},
{"learn":[0.257244243],"iteration":40,"passed_time":0.3373100301,"remaining_time":7.889763875},
{"learn":[0.2542098797],"iteration":41,"passed_time":0.342090898,"remaining_time":7.802930482},
{"learn":[0.2519136036],"iteration":42,"passed_time":0.3469160787,"remaining_time":7.720899705},
{"learn":[0.2497270259],"iteration":43,"passed_time":0.3515960729,"remaining_time":7.639223766},
{"learn":[0.2473010361],"iteration":44,"passed_time":0.3562427656,"remaining_time":7.560263136},
{"learn":[0.2449376598],"iteration":45,"passed_time":0.3610203117,"remaining_time":7.487247334},
{"learn":[0.2428296614],"iteration":46,"passed_time":0.3653311235,"remaining_time":7.407671503},
{"learn":[0.2409450034],"iteration":47,"passed_time":0.3696933838,"remaining_time":7.332252112},
{"learn":[0.2391295829],"iteration":48,"passed_time":0.3740121111,"remaining_time":7.258888115},
{"learn":[0.2370426847],"iteration":49,"passed_time":0.379324854,"remaining_time":7.207172225},
{"learn":[0.2356404929],"iteration":50,"passed_time":0.3839634962,"remaining_time":7.144732508},
{"learn":[0.2339340775],"iteration":51,"passed_time":0.3885193281,"remaining_time":7.083006212},
{"learn":[0.23218306],"iteration":52,"passed_time":0.3931468697,"remaining_time":7.024718596},
{"learn":[0.2304924124],"iteration":53,"passed_time":0.3978574464,"remaining_time":6.969873043},
{"learn":[0.2289485056],"iteration":54,"passed_time":0.4023845817,"remaining_time":6.913698721},
{"learn":[0.2277002511],"iteration":55,"passed_time":0.4070533941,"remaining_time":6.861757215},
{"learn":[0.2262537554],"iteration":56,"passed_time":0.4145358482,"remaining_time":6.858022892},
{"learn":[0.22476446],"iteration":57,"passed_time":0.419643678,"remaining_time":6.815592149},
{"learn":[0.2235018511],"iteration":58,"passed_time":0.4244579845,"remaining_time":6.769745142},
{"learn":[0.2223454852],"iteration":59,"passed_time":0.4290366505,"remaining_time":6.72157419},
{"learn":[0.2211182675],"iteration":60,"passed_time":0.4336124298,"remaining_time":6.674788059},
{"learn":[0.2199206857],"iteration":61,"passed_time":0.4383137913,"remaining_time":6.631263487},
{"learn":[0.2187620775],"iteration":62,"passed_time":0.4432158344,"remaining_time":6.59195614},
{"learn":[0.2174936299],"iteration":63,"passed_time":0.4478642176,"remaining_time":6.550014182},
{"learn":[0.2164204003],"iteration":64,"passed_time":0.4524278334,"remaining_time":6.508000373},
{"learn":[0.2149728197],"iteration":65,"passed_time":0.457181572,"remaining_time":6.469811943},
{"learn":[0.2137708044],"iteration":66,"passed_time":0.4619036013,"remaining_time":6.43218},
{"learn":[0.2125345206],"iteration":67,"passed_time":0.4667189856,"remaining_time":6.396795509},
{"learn":[0.2115234552],"iteration":68,"passed_time":0.4716143509,"remaining_time":6.363376242},
{"learn":[0.2103289116],"iteration":69,"passed_time":0.4765132044,"remaining_time":6.330818287},
{"learn":[0.209455915],"iteration":70,"passed_time":0.4812962845,"remaining_time":6.297524624},
{"learn":[0.2082460761],"iteration":71,"passed_time":0.486114248,"remaining_time":6.265472529},
{"learn":[0.2072741778],"iteration":72,"passed_time":0.4910588163,"remaining_time":6.235774284},
{"learn":[0.2061710237],"iteration":73,"passed_time":0.4957769428,"remaining_time":6.203911473},
{"learn":[0.2051370107],"iteration":74,"passed_time":0.500420831,"remaining_time":6.171856916},
{"learn":[0.2043927475],"iteration":75,"passed_time":0.5052579594,"remaining_time":6.142873085},
{"learn":[0.2033581943],"iteration":76,"passed_time":0.5100571175,"remaining_time":6.114061292},
{"learn":[0.2024504696],"iteration":77,"passed_time":0.5147614288,"remaining_time":6.084744068},
{"learn":[0.2015848415],"iteration":78,"passed_time":0.5196027136,"remaining_time":6.057646826},
{"learn":[0.2009089148],"iteration":79,"passed_time":0.5242576798,"remaining_time":6.028963317},
{"learn":[0.200049976],"iteration":80,"passed_time":0.5290079634,"remaining_time":6.001954548},
{"learn":[0.1992636413],"iteration":81,"passed_time":0.5337432113,"remaining_time":5.975320341},
{"learn":[0.1983872445],"iteration":82,"passed_time":0.5386261117,"remaining_time":5.950845114},
{"learn":[0.1978186075],"iteration":83,"passed_time":0.5433727861,"remaining_time":5.925350858},
{"learn":[0.1971368966],"iteration":84,"passed_time":0.548036593,"remaining_time":5.899452736},
{"learn":[0.1964068548],"iteration":85,"passed_time":0.5530573416,"remaining_time":5.877841979},
{"learn":[0.1956731341],"iteration":86,"passed_time":0.5586187604,"remaining_time":5.862286532},
{"learn":[0.1950546028],"iteration":87,"passed_time":0.5633783149,"remaining_time":5.838647991},
{"learn":[0.19435597],"iteration":88,"passed_time":0.5684386594,"remaining_time":5.81851257},
{"learn":[0.1936147788],"iteration":89,"passed_time":0.5730919661,"remaining_time":5.794596546},
{"learn":[0.1927771065],"iteration":90,"passed_time":0.5776614334,"remaining_time":5.770266406},
{"learn":[0.1919795357],"iteration":91,"passed_time":0.5830455368,"remaining_time":5.754405951},
{"learn":[0.1912816094],"iteration":92,"passed_time":0.5883199637,"remaining_time":5.737701151},
{"learn":[0.1907023677],"iteration":93,"passed_time":0.593092416,"remaining_time":5.716401371},
{"learn":[0.1901601813],"iteration":94,"passed_time":0.5978064898,"remaining_time":5.694893403},
{"learn":[0.1895555067],"iteration":95,"passed_time":0.6026425887,"remaining_time":5.674884377},
{"learn":[0.1890356639],"iteration":96,"passed_time":0.6074412051,"remaining_time":5.65483926},
{"learn":[0.1882179997],"iteration":97,"passed_time":0.6121982526,"remaining_time":5.634722692},
{"learn":[0.1876070394],"iteration":98,"passed_time":0.6168270663,"remaining_time":5.613749361},
{"learn":[0.1870534178],"iteration":99,"passed_time":0.6216679409,"remaining_time":5.595011469},
{"learn":[0.1863010698],"iteration":100,"passed_time":0.626317871,"remaining_time":5.574849168},
{"learn":[0.1857311261],"iteration":101,"passed_time":0.6310423701,"remaining_time":5.555647533},
{"learn":[0.1850373614],"iteration":102,"passed_time":0.635911468,"remaining_time":5.537986279},
{"learn":[0.1845400677],"iteration":103,"passed_time":0.6406650478,"remaining_time":5.519575796},
{"learn":[0.1840173655],"iteration":104,"passed_time":0.6453741921,"remaining_time":5.501046685},
{"learn":[0.1834961273],"iteration":105,"passed_time":0.6502816704,"remaining_time":5.484451069},
{"learn":[0.182814246],"iteration":106,"passed_time":0.6553060671,"remaining_time":5.4690497},
{"learn":[0.1822768039],"iteration":107,"passed_time":0.6599903293,"remaining_time":5.451031238},
{"learn":[0.1816852556],"iteration":108,"passed_time":0.6647141168,"remaining_time":5.433580533},
{"learn":[0.1811460617],"iteration":109,"passed_time":0.6696838881,"remaining_time":5.418351458},
{"learn":[0.18065376],"iteration":110,"passed_time":0.6749462901,"remaining_time":5.405650918},
{"learn":[0.1800514523],"iteration":111,"passed_time":0.6797469645,"remaining_time":5.389422362},
{"learn":[0.1796104538],"iteration":112,"passed_time":0.6835026825,"remaining_time":5.365193623},
{"learn":[0.1785042702],"iteration":113,"passed_time":0.6874516951,"remaining_time":5.342826332},
{"learn":[0.177834375],"iteration":114,"passed_time":0.6919254658,"remaining_time":5.324817715},
{"learn":[0.1772921521],"iteration":115,"passed_time":0.6968154991,"remaining_time":5.310214666},
{"learn":[0.1767729517],"iteration":116,"passed_time":0.7015304494,"remaining_time":5.294456297},
{"learn":[0.1760142546],"iteration":117,"passed_time":0.7062842018,"remaining_time":5.279175135},
{"learn":[0.1755906272],"iteration":118,"passed_time":0.7109307962,"remaining_time":5.263277575},
{"learn":[0.1750766291],"iteration":119,"passed_time":0.7160522481,"remaining_time":5.251049819},
{"learn":[0.1746382396],"iteration":120,"passed_time":0.7207405158,"remaining_time":5.235792672},
{"learn":[0.1741966437],"iteration":121,"passed_time":0.725458281,"remaining_time":5.220921071},
{"learn":[0.1735732646],"iteration":122,"passed_time":0.7302011342,"remaining_time":5.206393453},
{"learn":[0.1731562349],"iteration":123,"passed_time":0.734805119,"remaining_time":5.191042615},
{"learn":[0.1725316251],"iteration":124,"passed_time":0.7396881726,"remaining_time":5.177817208},
{"learn":[0.1720840791],"iteration":125,"passed_time":0.7444733118,"remaining_time":5.164045036},
{"learn":[0.1715754886],"iteration":126,"passed_time":0.7491721285,"remaining_time":5.149821009},
{"learn":[0.1710370777],"iteration":127,"passed_time":0.7538277767,"remaining_time":5.135451729},
{"learn":[0.1706155508],"iteration":128,"passed_time":0.7584374449,"remaining_time":5.120922593},
{"learn":[0.1702477277],"iteration":129,"passed_time":0.7629662607,"remaining_time":5.106004975},
{"learn":[0.1697855292],"iteration":130,"passed_time":0.7674376548,"remaining_time":5.090865054},
{"learn":[0.1693773202],"iteration":131,"passed_time":0.7720034336,"remaining_time":5.076507427},
{"learn":[0.1686875456],"iteration":132,"passed_time":0.7767366801,"remaining_time":5.063388734},
{"learn":[0.168180855],"iteration":133,"passed_time":0.7814032459,"remaining_time":5.049964261},
{"learn":[0.1677431441],"iteration":134,"passed_time":0.7858817048,"remaining_time":5.035464257},
{"learn":[0.1670819918],"iteration":135,"passed_time":0.7904862646,"remaining_time":5.02191274},
{"learn":[0.1667131587],"iteration":136,"passed_time":0.7952411848,"remaining_time":5.009438996},
{"learn":[0.1660806547],"iteration":137,"passed_time":0.7997405791,"remaining_time":4.995481009},
{"learn":[0.165680681],"iteration":138,"passed_time":0.8043193983,"remaining_time":4.982151093},
{"learn":[0.1652681351],"iteration":139,"passed_time":0.809604574,"remaining_time":4.97328524},
{"learn":[0.1648446752],"iteration":140,"passed_time":0.8165139837,"remaining_time":4.974365333},
{"learn":[0.164400844],"iteration":141,"passed_time":0.8216239164,"remaining_time":4.964460002},
{"learn":[0.1640147164],"iteration":142,"passed_time":0.8263343061,"remaining_time":4.952227275},
{"learn":[0.1635967344],"iteration":143,"passed_time":0.8308725404,"remaining_time":4.939075657},
{"learn":[0.1631530262],"iteration":144,"passed_time":0.8352794044,"remaining_time":4.925268212},
{"learn":[0.1628597513],"iteration":145,"passed_time":0.8398228319,"remaining_time":4.912388345},
{"learn":[0.1624883736],"iteration":146,"passed_time":0.8442927209,"remaining_time":4.899195176},
{"learn":[0.1619593058],"iteration":147,"passed_time":0.8487607434,"remaining_time":4.886109145},
{"learn":[0.1617158076],"iteration":148,"passed_time":0.8531973731,"remaining_time":4.872959493},
{"learn":[0.1614484756],"iteration":149,"passed_time":0.8579079615,"remaining_time":4.861478448},
{"learn":[0.1609088124],"iteration":150,"passed_time":0.8624288707,"remaining_time":4.849020604},
{"learn":[0.1605307881],"iteration":151,"passed_time":0.8670013661,"remaining_time":4.83695499},
{"learn":[0.1600484477],"iteration":152,"passed_time":0.8716450056,"remaining_time":4.825381175},
{"learn":[0.1596642827],"iteration":153,"passed_time":0.8761124953,"remaining_time":4.812929682},
{"learn":[0.1590563512],"iteration":154,"passed_time":0.8806089698,"remaining_time":4.800739222},
{"learn":[0.1588304051],"iteration":155,"passed_time":0.885080808,"remaining_time":4.788514115},
{"learn":[0.1583704068],"iteration":156,"passed_time":0.8897860711,"remaining_time":4.777641133},
{"learn":[0.1580363059],"iteration":157,"passed_time":0.8943494749,"remaining_time":4.76609024},
{"learn":[0.1576147974],"iteration":158,"passed_time":0.8988485667,"remaining_time":4.754287073},
{"learn":[0.1572273501],"iteration":159,"passed_time":0.9033397392,"remaining_time":4.742533631},
{"learn":[0.1568657522],"iteration":160,"passed_time":0.9078778075,"remaining_time":4.731114786},
{"learn":[0.1564724717],"iteration":161,"passed_time":0.9123746449,"remaining_time":4.719567607},
{"learn":[0.1561316827],"iteration":162,"passed_time":0.9168965819,"remaining_time":4.708235822},
{"learn":[0.1556739131],"iteration":163,"passed_time":0.9215370807,"remaining_time":4.69759146},
{"learn":[0.1551620432],"iteration":164,"passed_time":0.9260737254,"remaining_time":4.686494307},
{"learn":[0.1548133286],"iteration":165,"passed_time":0.9305030256,"remaining_time":4.674936888},
{"learn":[0.1544306177],"iteration":166,"passed_time":0.9351552561,"remaining_time":4.664576817},
{"learn":[0.1539869915],"iteration":167,"passed_time":0.9398506274,"remaining_time":4.654498345},
{"learn":[0.1537509186],"iteration":168,"passed_time":0.9444550207,"remaining_time":4.644036226},
{"learn":[0.153476702],"iteration":169,"passed_time":0.9490374258,"remaining_time":4.633535667},
{"learn":[0.1530748353],"iteration":170,"passed_time":0.9536473508,"remaining_time":4.623237742},
{"learn":[0.152611158],"iteration":171,"passed_time":0.958622156,"remaining_time":4.614762472},
{"learn":[0.1522056383],"iteration":172,"passed_time":0.9631809921,"remaining_time":4.604339193},
{"learn":[0.1519673146],"iteration":173,"passed_time":0.9677655872,"remaining_time":4.594105604},
{"learn":[0.1515147536],"iteration":174,"passed_time":0.9723496606,"remaining_time":4.583934114},
{"learn":[0.1512623211],"iteration":175,"passed_time":0.9767527895,"remaining_time":4.572978969},
{"learn":[0.1509746127],"iteration":176,"passed_time":0.9811965782,"remaining_time":4.562286914},
{"learn":[0.1506460437],"iteration":177,"passed_time":0.9855992531,"remaining_time":4.551475202},
{"learn":[0.1503608045],"iteration":178,"passed_time":0.9903113394,"remaining_time":4.542154244},
{"learn":[0.1499625691],"iteration":179,"passed_time":0.9947976284,"remaining_time":4.531855862},
{"learn":[0.1496576404],"iteration":180,"passed_time":0.9992454936,"remaining_time":4.521447841},
{"learn":[0.1492023743],"iteration":181,"passed_time":1.003779756,"remaining_time":4.511493627},
{"learn":[0.1487760719],"iteration":182,"passed_time":1.008278872,"remaining_time":4.50144174},
{"learn":[0.1483044518],"iteration":183,"passed_time":1.012864644,"remaining_time":4.491834509},
{"learn":[0.1480872195],"iteration":184,"passed_time":1.017177775,"remaining_time":4.48108047},
{"learn":[0.147714682],"iteration":185,"passed_time":1.021920392,"remaining_time":4.472275264},
{"learn":[0.1474577649],"iteration":186,"passed_time":1.026281707,"remaining_time":4.461855765},
{"learn":[0.1471747238],"iteration":187,"passed_time":1.030870303,"remaining_time":4.452482374},
{"learn":[0.1468893879],"iteration":188,"passed_time":1.035527049,"remaining_time":4.443452046},
{"learn":[0.1465230661],"iteration":189,"passed_time":1.040174157,"remaining_time":4.43442667},
{"learn":[0.1462548738],"iteration":190,"passed_time":1.044874546,"remaining_time":4.425672814},
{"learn":[0.1459019797],"iteration":191,"passed_time":1.049456561,"remaining_time":4.416463028},
{"learn":[0.1456146925],"iteration":192,"passed_time":1.054265535,"remaining_time":4.408250189},
{"learn":[0.1452717811],"iteration":193,"passed_time":1.058989639,"remaining_time":4.399719841},
{"learn":[0.1449408204],"iteration":194,"passed_time":1.063446648,"remaining_time":4.390125904},
{"learn":[0.1447022273],"iteration":195,"passed_time":1.067885841,"remaining_time":4.380511306},
{"learn":[0.1444443266],"iteration":196,"passed_time":1.072514454,"remaining_time":4.371721351},
{"learn":[0.1440373883],"iteration":197,"passed_time":1.076927564,"remaining_time":4.362100535},
{"learn":[0.1437948012],"iteration":198,"passed_time":1.081383783,"remaining_time":4.35270558},
{"learn":[0.1434958497],"iteration":199,"passed_time":1.08613695,"remaining_time":4.344547801},
{"learn":[0.1431777252],"iteration":200,"passed_time":1.091211424,"remaining_time":4.337701134},
{"learn":[0.1430471429],"iteration":201,"passed_time":1.095818389,"remaining_time":4.329025122},
{"learn":[0.1427181242],"iteration":202,"passed_time":1.1001532,"remaining_time":4.31932069},
{"learn":[0.1423965962],"iteration":203,"passed_time":1.104758903,"remaining_time":4.310725917},
{"learn":[0.1420478726],"iteration":204,"passed_time":1.109598376,"remaining_time":4.303076629},
{"learn":[0.1416559047],"iteration":205,"passed_time":1.114085792,"remaining_time":4.294097665},
{"learn":[0.1413572555],"iteration":206,"passed_time":1.118648282,"remaining_time":4.285449698},
{"learn":[0.1410653956],"iteration":207,"passed_time":1.123103665,"remaining_time":4.276433185},
{"learn":[0.1407693256],"iteration":208,"passed_time":1.127836236,"remaining_time":4.26850939},
{"learn":[0.1404417266],"iteration":209,"passed_time":1.132424932,"remaining_time":4.260074744},
{"learn":[0.14013563],"iteration":210,"passed_time":1.136894662,"remaining_time":4.251231699},
{"learn":[0.1399281705],"iteration":211,"passed_time":1.141711577,"remaining_time":4.243720391},
{"learn":[0.1395809047],"iteration":212,"passed_time":1.146378332,"remaining_time":4.235679566},
{"learn":[0.1392284053],"iteration":213,"passed_time":1.150932698,"remaining_time":4.227257481},
{"learn":[0.1389453293],"iteration":214,"passed_time":1.155438188,"remaining_time":4.21869292},
{"learn":[0.1388169284],"iteration":215,"passed_time":1.15994595,"remaining_time":4.210174191},
{"learn":[0.1386487414],"iteration":216,"passed_time":1.164442094,"remaining_time":4.201650503},
{"learn":[0.1383077536],"iteration":217,"passed_time":1.16883054,"remaining_time":4.192777443},
{"learn":[0.1380804576],"iteration":218,"passed_time":1.173302693,"remaining_time":4.184243849},
{"learn":[0.137828191],"iteration":219,"passed_time":1.177862841,"remaining_time":4.176059163},
{"learn":[0.1376343325],"iteration":220,"passed_time":1.182357978,"remaining_time":4.167678122},
{"learn":[0.1373206288],"iteration":221,"passed_time":1.186970888,"remaining_time":4.159744824},
{"learn":[0.1371137665],"iteration":222,"passed_time":1.191884586,"remaining_time":4.152889342},
{"learn":[0.1369042932],"iteration":223,"passed_time":1.196391413,"remaining_time":4.144641682},
{"learn":[0.1366399636],"iteration":224,"passed_time":1.200942213,"remaining_time":4.136578733},
{"learn":[0.1363961718],"iteration":225,"passed_time":1.205654491,"remaining_time":4.129099895},
{"learn":[0.1359530178],"iteration":226,"passed_time":1.232846129,"remaining_time":4.198194088},
{"learn":[0.1357315547],"iteration":227,"passed_time":1.249234615,"remaining_time":4.229864572},
{"learn":[0.1355164467],"iteration":228,"passed_time":1.261054353,"remaining_time":4.245733215},
{"learn":[0.1352445748],"iteration":229,"passed_time":1.270666255,"remaining_time":4.253969636},
{"learn":[0.1350192181],"iteration":230,"passed_time":1.280619088,"remaining_time":4.263186486},
{"learn":[0.1347028105],"iteration":231,"passed_time":1.290801121,"remaining_time":4.272996816},
{"learn":[0.1344208725],"iteration":232,"passed_time":1.300616983,"remaining_time":4.281430155},
{"learn":[0.1342296012],"iteration":233,"passed_time":1.31068224,"remaining_time":4.290523913},
{"learn":[0.1339807503],"iteration":234,"passed_time":1.320449584,"remaining_time":4.298484816},
{"learn":[0.1337645209],"iteration":235,"passed_time":1.330438261,"remaining_time":4.307011998},
{"learn":[0.1334546917],"iteration":236,"passed_time":1.340501665,"remaining_time":4.315623503},
{"learn":[0.1331684739],"iteration":237,"passed_time":1.350338964,"remaining_time":4.323354163},
{"learn":[0.1328812108],"iteration":238,"passed_time":1.361546233,"remaining_time":4.33529993},
{"learn":[0.1326861504],"iteration":239,"passed_time":1.369094334,"remaining_time":4.33546539},
{"learn":[0.1323995638],"iteration":240,"passed_time":1.376677657,"remaining_time":4.335677766},
{"learn":[0.1320858965],"iteration":241,"passed_time":1.384100999,"remaining_time":4.335324617},
{"learn":[0.1318662992],"iteration":242,"passed_time":1.391732295,"remaining_time":4.335561101},
{"learn":[0.131529073],"iteration":243,"passed_time":1.399038415,"remaining_time":4.334725582},
{"learn":[0.1311998418],"iteration":244,"passed_time":1.406563266,"remaining_time":4.334511289},
{"learn":[0.1308118349],"iteration":245,"passed_time":1.414412138,"remaining_time":4.335230701},
{"learn":[0.1304992058],"iteration":246,"passed_time":1.421823191,"remaining_time":4.334546003},
{"learn":[0.1302145507],"iteration":247,"passed_time":1.429328914,"remaining_time":4.334094127},
{"learn":[0.1300312187],"iteration":248,"passed_time":1.436941269,"remaining_time":4.333907202},
{"learn":[0.1298917862],"iteration":249,"passed_time":1.444424916,"remaining_time":4.333274747},
{"learn":[0.1296490471],"iteration":250,"passed_time":1.451885969,"remaining_time":4.332520282},
{"learn":[0.1293443722],"iteration":251,"passed_time":1.4594743,"remaining_time":4.332090382},
{"learn":[0.1291768097],"iteration":252,"passed_time":1.466809685,"remaining_time":4.330857053},
{"learn":[0.1288663337],"iteration":253,"passed_time":1.473831687,"remaining_time":4.32865527},
{"learn":[0.1286041011],"iteration":254,"passed_time":1.479895418,"remaining_time":4.323616025},
{"learn":[0.1283086856],"iteration":255,"passed_time":1.486093213,"remaining_time":4.3189584},
{"learn":[0.1280340448],"iteration":256,"passed_time":1.491963689,"remaining_time":4.313342493},
{"learn":[0.127820653],"iteration":257,"passed_time":1.497037675,"remaining_time":4.305433934},
{"learn":[0.1276304436],"iteration":258,"passed_time":1.501835293,"remaining_time":4.296756572},
{"learn":[0.1273965923],"iteration":259,"passed_time":1.506588733,"remaining_time":4.287983316},
{"learn":[0.1272217825],"iteration":260,"passed_time":1.511836749,"remaining_time":4.280641218},
{"learn":[0.1270687755],"iteration":261,"passed_time":1.51672416,"remaining_time":4.272299352},
{"learn":[0.126847919],"iteration":262,"passed_time":1.521490933,"remaining_time":4.263645695},
{"learn":[0.1265971453],"iteration":263,"passed_time":1.526359129,"remaining_time":4.255304238},
{"learn":[0.1262866667],"iteration":264,"passed_time":1.531321343,"remaining_time":4.247249764},
{"learn":[0.1260163958],"iteration":265,"passed_time":1.536599184,"remaining_time":4.240089478},
{"learn":[0.1257199914],"iteration":266,"passed_time":1.541480961,"remaining_time":4.231855972},
{"learn":[0.1255193542],"iteration":267,"passed_time":1.546463933,"remaining_time":4.223923877},
{"learn":[0.1253554124],"iteration":268,"passed_time":1.551456201,"remaining_time":4.216038969},
{"learn":[0.1251696343],"iteration":269,"passed_time":1.55631102,"remaining_time":4.20780387},
{"learn":[0.1248627875],"iteration":270,"passed_time":1.561469983,"remaining_time":4.200411873},
{"learn":[0.1246633266],"iteration":271,"passed_time":1.566435723,"remaining_time":4.192519141},
{"learn":[0.1243900196],"iteration":272,"passed_time":1.571023558,"remaining_time":4.183641491},
{"learn":[0.1241854289],"iteration":273,"passed_time":1.57558454,"remaining_time":4.174724001},
{"learn":[0.1240094788],"iteration":274,"passed_time":1.580287491,"remaining_time":4.166212475},
{"learn":[0.1237721241],"iteration":275,"passed_time":1.58473112,"remaining_time":4.1570483},
{"learn":[0.1233527331],"iteration":276,"passed_time":1.589372498,"remaining_time":4.148434355},
{"learn":[0.1230949969],"iteration":277,"passed_time":1.593918633,"remaining_time":4.139601629},
{"learn":[0.1228867453],"iteration":278,"passed_time":1.598426365,"remaining_time":4.130700391},
{"learn":[0.1225783493],"iteration":279,"passed_time":1.602825907,"remaining_time":4.121552333},
{"learn":[0.1223552838],"iteration":280,"passed_time":1.607115515,"remaining_time":4.11215678},
{"learn":[0.1220327058],"iteration":281,"passed_time":1.613139073,"remaining_time":4.10721225},
{"learn":[0.121822986],"iteration":282,"passed_time":1.620880051,"remaining_time":4.106611296},
{"learn":[0.1216173413],"iteration":283,"passed_time":1.624963988,"remaining_time":4.096740196},
{"learn":[0.1214000128],"iteration":284,"passed_time":1.629312544,"remaining_time":4.087573575},
{"learn":[0.1211457659],"iteration":285,"passed_time":1.633905308,"remaining_time":4.079050314},
{"learn":[0.1210282843],"iteration":286,"passed_time":1.638955707,"remaining_time":4.071691356},
{"learn":[0.1208222511],"iteration":287,"passed_time":1.643508555,"remaining_time":4.063118373},
{"learn":[0.1205912163],"iteration":288,"passed_time":1.64818466,"remaining_time":4.054876448},
{"learn":[0.1204181419],"iteration":289,"passed_time":1.652858555,"remaining_time":4.046653703},
{"learn":[0.1201677484],"iteration":290,"passed_time":1.658029008,"remaining_time":4.039665178},
{"learn":[0.1199641475],"iteration":291,"passed_time":1.662800656,"remaining_time":4.031722137},
{"learn":[0.1197298123],"iteration":292,"passed_time":1.6675056,"remaining_time":4.023639793},
{"learn":[0.119393786],"iteration":293,"passed_time":1.672375015,"remaining_time":4.015975377},
{"learn":[0.119178257],"iteration":294,"passed_time":1.67709634,"remaining_time":4.007976},
{"learn":[0.1190194823],"iteration":295,"passed_time":1.681950621,"remaining_time":4.000314991},
{"learn":[0.1187119318],"iteration":296,"passed_time":1.687185845,"remaining_time":3.993574575},
{"learn":[0.1185693942],"iteration":297,"passed_time":1.691809689,"remaining_time":3.985404033},
{"learn":[0.118429595],"iteration":298,"passed_time":1.69645561,"remaining_time":3.977308972},
{"learn":[0.1181871953],"iteration":299,"passed_time":1.701100027,"remaining_time":3.969233397},
{"learn":[0.1179611964],"iteration":300,"passed_time":1.706116427,"remaining_time":3.962044459},
{"learn":[0.1178507255],"iteration":301,"passed_time":1.710880569,"remaining_time":3.954286879},
{"learn":[0.1176718907],"iteration":302,"passed_time":1.715670147,"remaining_time":3.946607566},
{"learn":[0.1174247815],"iteration":303,"passed_time":1.720237332,"remaining_time":3.938438101},
{"learn":[0.1172425681],"iteration":304,"passed_time":1.724860282,"remaining_time":3.93041933},
{"learn":[0.1170433179],"iteration":305,"passed_time":1.730218613,"remaining_time":3.924090581},
{"learn":[0.1168634319],"iteration":306,"passed_time":1.734756531,"remaining_time":3.915916209},
{"learn":[0.1167003197],"iteration":307,"passed_time":1.738918789,"remaining_time":3.906921435},
{"learn":[0.116588772],"iteration":308,"passed_time":1.7430821,"remaining_time":3.897960295},
{"learn":[0.1164547395],"iteration":309,"passed_time":1.747307381,"remaining_time":3.889168042},
{"learn":[0.1161945787],"iteration":310,"passed_time":1.7518666,"remaining_time":3.881144976},
{"learn":[0.1159252447],"iteration":311,"passed_time":1.756198321,"remaining_time":3.872642452},
{"learn":[0.1155512031],"iteration":312,"passed_time":1.761201574,"remaining_time":3.865640515},
{"learn":[0.1153561748],"iteration":313,"passed_time":1.765789557,"remaining_time":3.857744065},
{"learn":[0.1151465088],"iteration":314,"passed_time":1.770359889,"remaining_time":3.849830236},
{"learn":[0.1149283648],"iteration":315,"passed_time":1.775081332,"remaining_time":3.842264654},
{"learn":[0.1147441616],"iteration":316,"passed_time":1.779672134,"remaining_time":3.834435545},
{"learn":[0.1145413401],"iteration":317,"passed_time":1.7842882,"remaining_time":3.826680983},
{"learn":[0.1143248757],"iteration":318,"passed_time":1.78903208,"remaining_time":3.819218955},
{"learn":[0.1141359358],"iteration":319,"passed_time":1.793518277,"remaining_time":3.81122634},
{"learn":[0.1138739198],"iteration":320,"passed_time":1.798063776,"remaining_time":3.803381008},
{"learn":[0.1136885497],"iteration":321,"passed_time":1.802520728,"remaining_time":3.795369732},
{"learn":[0.1134652707],"iteration":322,"passed_time":1.807189795,"remaining_time":3.787825049},
{"learn":[0.1131689303],"iteration":323,"passed_time":1.811741445,"remaining_time":3.780053137},
{"learn":[0.1130717166],"iteration":324,"passed_time":1.816225598,"remaining_time":3.772160858},
{"learn":[0.1129049858],"iteration":325,"passed_time":1.820736282,"remaining_time":3.764344338},
{"learn":[0.1127125439],"iteration":326,"passed_time":1.825246283,"remaining_time":3.756546632},
{"learn":[0.1125786507],"iteration":327,"passed_time":1.829767419,"remaining_time":3.748791786},
{"learn":[0.1124285033],"iteration":328,"passed_time":1.834374618,"remaining_time":3.741232124},
{"learn":[0.1122944355],"iteration":329,"passed_time":1.838869698,"remaining_time":3.733462721},
{"learn":[0.1120805466],"iteration":330,"passed_time":1.843352279,"remaining_time":3.725687838},
{"learn":[0.1119124353],"iteration":331,"passed_time":1.847996198,"remaining_time":3.718257411},
{"learn":[0.1117251807],"iteration":332,"passed_time":1.852855508,"remaining_time":3.711275147},
{"learn":[0.1115297127],"iteration":333,"passed_time":1.857425457,"remaining_time":3.703728607},
{"learn":[0.1113319474],"iteration":334,"passed_time":1.86194641,"remaining_time":3.696102576},
{"learn":[0.1111849683],"iteration":335,"passed_time":1.866454165,"remaining_time":3.688468945},
{"learn":[0.1109408666],"iteration":336,"passed_time":1.870969609,"remaining_time":3.680868994},
{"learn":[0.1107779448],"iteration":337,"passed_time":1.875376268,"remaining_time":3.673074228},
{"learn":[0.1105546793],"iteration":338,"passed_time":1.879957055,"remaining_time":3.665638977},
{"learn":[0.1102457988],"iteration":339,"passed_time":1.884816454,"remaining_time":3.658761352},
{"learn":[0.1100828065],"iteration":340,"passed_time":1.889583531,"remaining_time":3.651717146},
{"learn":[0.1099332385],"iteration":341,"passed_time":1.894003314,"remaining_time":3.644018073},
{"learn":[0.1096709137],"iteration":342,"passed_time":1.89858992,"remaining_time":3.63665766},
{"learn":[0.1095003148],"iteration":343,"passed_time":1.903105388,"remaining_time":3.629177716},
{"learn":[0.1093563056],"iteration":344,"passed_time":1.907526973,"remaining_time":3.621536716},
{"learn":[0.1090713755],"iteration":345,"passed_time":1.911967619,"remaining_time":3.613950355},
{"learn":[0.1089302539],"iteration":346,"passed_time":1.916493772,"remaining_time":3.606543035},
{"learn":[0.1087509636],"iteration":347,"passed_time":1.920942281,"remaining_time":3.599006802},
{"learn":[0.1086198154],"iteration":348,"passed_time":1.925760817,"remaining_time":3.592178486},
{"learn":[0.1084458589],"iteration":349,"passed_time":1.930084009,"remaining_time":3.584441731},
{"learn":[0.1082556401],"iteration":350,"passed_time":1.934416651,"remaining_time":3.576741899},
{"learn":[0.1081354421],"iteration":351,"passed_time":1.938726662,"remaining_time":3.569019536},
{"learn":[0.1079998802],"iteration":352,"passed_time":1.943308789,"remaining_time":3.561815258},
{"learn":[0.1078651863],"iteration":353,"passed_time":1.947631215,"remaining_time":3.554151878},
{"learn":[0.1075970739],"iteration":354,"passed_time":1.95195455,"remaining_time":3.546508971},
{"learn":[0.1074142643],"iteration":355,"passed_time":1.95648767,"remaining_time":3.539264212},
{"learn":[0.1072186395],"iteration":356,"passed_time":1.961863613,"remaining_time":3.53355267},
{"learn":[0.1069961377],"iteration":357,"passed_time":1.9666508,"remaining_time":3.526787188},
{"learn":[0.106692173],"iteration":358,"passed_time":1.970985735,"remaining_time":3.519225225},
{"learn":[0.1065135722],"iteration":359,"passed_time":1.975473529,"remaining_time":3.511952941},
{"learn":[0.1062320801],"iteration":360,"passed_time":1.979986434,"remaining_time":3.504740529},
{"learn":[0.1060518938],"iteration":361,"passed_time":1.98464554,"remaining_time":3.497800703},
{"learn":[0.1058977448],"iteration":362,"passed_time":1.989582493,"remaining_time":3.491361014},
{"learn":[0.1057517074],"iteration":363,"passed_time":1.994191551,"remaining_time":3.484356666},
{"learn":[0.1055358489],"iteration":364,"passed_time":1.998555544,"remaining_time":3.476939097},
{"learn":[0.1051717191],"iteration":365,"passed_time":2.002892386,"remaining_time":3.469491182},
{"learn":[0.1050391619],"iteration":366,"passed_time":2.008982807,"remaining_time":3.465084786},
{"learn":[0.1047277828],"iteration":367,"passed_time":2.015491034,"remaining_time":3.461386777},
{"learn":[0.1045044675],"iteration":368,"passed_time":2.020336514,"remaining_time":3.454830191},
{"learn":[0.1042899041],"iteration":369,"passed_time":2.024979032,"remaining_time":3.447937271},
{"learn":[0.1041520441],"iteration":370,"passed_time":2.029542642,"remaining_time":3.4409227},
{"learn":[0.1038013242],"iteration":371,"passed_time":2.034084452,"remaining_time":3.433884506},
{"learn":[0.1035870907],"iteration":372,"passed_time":2.038709425,"remaining_time":3.426999489},
{"learn":[0.1034602466],"iteration":373,"passed_time":2.043611633,"remaining_time":3.420590594},
{"learn":[0.1032826395],"iteration":374,"passed_time":2.04817886,"remaining_time":3.413631433},
{"learn":[0.1031087851],"iteration":375,"passed_time":2.052645139,"remaining_time":3.406517464},
{"learn":[0.1030210684],"iteration":376,"passed_time":2.057221802,"remaining_time":3.399599954},
{"learn":[0.1029112209],"iteration":377,"passed_time":2.062346331,"remaining_time":3.393596344},
{"learn":[0.1027468061],"iteration":378,"passed_time":2.066746218,"remaining_time":3.386410029},
{"learn":[0.102527545],"iteration":379,"passed_time":2.070806902,"remaining_time":3.378684945},
{"learn":[0.1023541306],"iteration":380,"passed_time":2.076255918,"remaining_time":3.373234681},
{"learn":[0.10215375],"iteration":381,"passed_time":2.080316468,"remaining_time":3.36553816},
{"learn":[0.1019009089],"iteration":382,"passed_time":2.084795613,"remaining_time":3.358534969},
{"learn":[0.1017668808],"iteration":383,"passed_time":2.089185852,"remaining_time":3.351402304},
{"learn":[0.1015844324],"iteration":384,"passed_time":2.094066294,"remaining_time":3.345066937},
{"learn":[0.1014227442],"iteration":385,"passed_time":2.099171766,"remaining_time":3.339097058},
{"learn":[0.1012490116],"iteration":386,"passed_time":2.103991584,"remaining_time":3.332679176},
{"learn":[0.10109126],"iteration":387,"passed_time":2.108643883,"remaining_time":3.326005301},
{"learn":[0.1009919644],"iteration":388,"passed_time":2.11407243,"remaining_time":3.320561065},
{"learn":[0.1007994568],"iteration":389,"passed_time":2.118810741,"remaining_time":3.314037312},
{"learn":[0.1005766397],"iteration":390,"passed_time":2.123439926,"remaining_time":3.307352724},
{"learn":[0.1003661842],"iteration":391,"passed_time":2.128091335,"remaining_time":3.30071309},
{"learn":[0.100060586],"iteration":392,"passed_time":2.13292333,"remaining_time":3.294362497},
{"learn":[0.09993017233],"iteration":393,"passed_time":2.137731996,"remaining_time":3.28798373},
{"learn":[0.0998351636],"iteration":394,"passed_time":2.14241059,"remaining_time":3.281413689},
{"learn":[0.09964142585],"iteration":395,"passed_time":2.147318907,"remaining_time":3.275203586},
{"learn":[0.09943359764],"iteration":396,"passed_time":2.152101774,"remaining_time":3.268809495},
{"learn":[0.0992167985],"iteration":397,"passed_time":2.156836282,"remaining_time":3.262350357},
{"learn":[0.09903360707],"iteration":398,"passed_time":2.161522422,"remaining_time":3.255827007},
{"learn":[0.09891325056],"iteration":399,"passed_time":2.166246511,"remaining_time":3.249369766},
{"learn":[0.09871090381],"iteration":400,"passed_time":2.171004723,"remaining_time":3.242972143},
{"learn":[0.09858585373],"iteration":401,"passed_time":2.175631227,"remaining_time":3.23638675},
{"learn":[0.09843480853],"iteration":402,"passed_time":2.180255855,"remaining_time":3.229808302},
{"learn":[0.09828740488],"iteration":403,"passed_time":2.184981308,"remaining_time":3.223388266},
{"learn":[0.09806034267],"iteration":404,"passed_time":2.189725277,"remaining_time":3.217003803},
{"learn":[0.09791528598],"iteration":405,"passed_time":2.194046914,"remaining_time":3.210009524},
{"learn":[0.09778960939],"iteration":406,"passed_time":2.19880007,"remaining_time":3.203657104},
{"learn":[0.09763003338],"iteration":407,"passed_time":2.203175275,"remaining_time":3.196764124},
{"learn":[0.09749847132],"iteration":408,"passed_time":2.207507106,"remaining_time":3.189820782},
{"learn":[0.09737736058],"iteration":409,"passed_time":2.211950922,"remaining_time":3.183051327},
{"learn":[0.09720912289],"iteration":410,"passed_time":2.216330955,"remaining_time":3.176201782},
{"learn":[0.09703267251],"iteration":411,"passed_time":2.220712693,"remaining_time":3.169366659},
{"learn":[0.09686756639],"iteration":412,"passed_time":2.225427124,"remaining_time":3.163016275},
{"learn":[0.09673070537],"iteration":413,"passed_time":2.229693253,"remaining_time":3.156039242},
{"learn":[0.09661812817],"iteration":414,"passed_time":2.234010068,"remaining_time":3.149146723},
{"learn":[0.09639485804],"iteration":415,"passed_time":2.238503071,"remaining_time":3.142513926},
{"learn":[0.09622471606],"iteration":416,"passed_time":2.243040889,"remaining_time":3.135954049},
{"learn":[0.0960367459],"iteration":417,"passed_time":2.247470233,"remaining_time":3.129252813},
{"learn":[0.09590738151],"iteration":418,"passed_time":2.251821257,"remaining_time":3.122453819},
{"learn":[0.09575713079],"iteration":419,"passed_time":2.256195962,"remaining_time":3.115699185},
{"learn":[0.09558513672],"iteration":420,"passed_time":2.260514704,"remaining_time":3.108878893},
{"learn":[0.09548073672],"iteration":421,"passed_time":2.264846669,"remaining_time":3.102088565},
{"learn":[0.09537512539],"iteration":422,"passed_time":2.269242993,"remaining_time":3.095397652},
{"learn":[0.09518273666],"iteration":423,"passed_time":2.273840022,"remaining_time":3.088990218},
{"learn":[0.0949398519],"iteration":424,"passed_time":2.278187292,"remaining_time":3.082253395},
{"learn":[0.09477287643],"iteration":425,"passed_time":2.282458375,"remaining_time":3.075425135},
{"learn":[0.09461254582],"iteration":426,"passed_time":2.287574857,"remaining_time":3.069743309},
{"learn":[0.09434019148],"iteration":427,"passed_time":2.292080316,"remaining_time":3.063247525},
{"learn":[0.09418190074],"iteration":428,"passed_time":2.29647484,"remaining_time":3.056613365},
{"learn":[0.09402295943],"iteration":429,"passed_time":2.300804555,"remaining_time":3.049903712},
{"learn":[0.09391591794],"iteration":430,"passed_time":2.305133073,"remaining_time":3.043203523},
{"learn":[0.09378573563],"iteration":431,"passed_time":2.309512746,"remaining_time":3.036581573},
{"learn":[0.09363060802],"iteration":432,"passed_time":2.313844674,"remaining_time":3.02990746},
{"learn":[0.09351501378],"iteration":433,"passed_time":2.318299917,"remaining_time":3.023404961},
{"learn":[0.09335691392],"iteration":434,"passed_time":2.323197555,"remaining_time":3.017486479},
{"learn":[0.09317710215],"iteration":435,"passed_time":2.32747284,"remaining_time":3.010767619},
{"learn":[0.09302524955],"iteration":436,"passed_time":2.331744576,"remaining_time":3.00405537},
{"learn":[0.09287928262],"iteration":437,"passed_time":2.33615565,"remaining_time":2.997533049},
{"learn":[0.09266938002],"iteration":438,"passed_time":2.341271685,"remaining_time":2.99192122},
{"learn":[0.09255353659],"iteration":439,"passed_time":2.345782301,"remaining_time":2.985541111},
{"learn":[0.09239752251],"iteration":440,"passed_time":2.350192223,"remaining_time":2.979041843},
{"learn":[0.09227468506],"iteration":441,"passed_time":2.354689499,"remaining_time":2.972662309},
{"learn":[0.09211242918],"iteration":442,"passed_time":2.358997095,"remaining_time":2.966052781},
{"learn":[0.0918816918],"iteration":443,"passed_time":2.363402298,"remaining_time":2.959575851},
{"learn":[0.09174708181],"iteration":444,"passed_time":2.367936233,"remaining_time":2.953268785},
{"learn":[0.09160247812],"iteration":445,"passed_time":2.372314814,"remaining_time":2.946776698},
{"learn":[0.09140485794],"iteration":446,"passed_time":2.376656797,"remaining_time":2.94024879},
{"learn":[0.09118791758],"iteration":447,"passed_time":2.381049039,"remaining_time":2.933792566},
{"learn":[0.09100117662],"iteration":448,"passed_time":2.385927868,"remaining_time":2.927942662},
{"learn":[0.09086956045],"iteration":449,"passed_time":2.39039122,"remaining_time":2.921589269},
{"learn":[0.09065530107],"iteration":450,"passed_time":2.394727764,"remaining_time":2.915089895},
{"learn":[0.09048246407],"iteration":451,"passed_time":2.399171913,"remaining_time":2.908730549},
{"learn":[0.09026725951],"iteration":452,"passed_time":2.40369832,"remaining_time":2.902478987},
{"learn":[0.09013710182],"iteration":453,"passed_time":2.408182393,"remaining_time":2.896184111},
{"learn":[0.0899432595],"iteration":454,"passed_time":2.412625033,"remaining_time":2.889847567},
{"learn":[0.08974394471],"iteration":455,"passed_time":2.416965509,"remaining_time":2.883397449},
{"learn":[0.08952937107],"iteration":456,"passed_time":2.421425875,"remaining_time":2.877099015},
{"learn":[0.08930115728],"iteration":457,"passed_time":2.425780399,"remaining_time":2.870683354},
{"learn":[0.08921533182],"iteration":458,"passed_time":2.430041859,"remaining_time":2.864166985},
{"learn":[0.08908192364],"iteration":459,"passed_time":2.434378288,"remaining_time":2.857748425},
{"learn":[0.08896135626],"iteration":460,"passed_time":2.438764077,"remaining_time":2.851396611},
{"learn":[0.08874995596],"iteration":461,"passed_time":2.443117785,"remaining_time":2.845015948},
{"learn":[0.08856294322],"iteration":462,"passed_time":2.447421672,"remaining_time":2.838586258},
{"learn":[0.08847119911],"iteration":463,"passed_time":2.452628375,"remaining_time":2.83320864},
{"learn":[0.08827568255],"iteration":464,"passed_time":2.459304741,"remaining_time":2.829522659},
{"learn":[0.0880638991],"iteration":465,"passed_time":2.464063993,"remaining_time":2.823626979},
{"learn":[0.08782630598],"iteration":466,"passed_time":2.46862142,"remaining_time":2.817505818},
{"learn":[0.08769770511],"iteration":467,"passed_time":2.472936207,"remaining_time":2.811115517},
{"learn":[0.08751233402],"iteration":468,"passed_time":2.477224706,"remaining_time":2.804704305},
{"learn":[0.08737855484],"iteration":469,"passed_time":2.48178462,"remaining_time":2.798608189},
{"learn":[0.08723623606],"iteration":470,"passed_time":2.48645844,"remaining_time":2.792646528},
{"learn":[0.08715956435],"iteration":471,"passed_time":2.490947678,"remaining_time":2.786483844},
{"learn":[0.08707442333],"iteration":472,"passed_time":2.495365553,"remaining_time":2.780248724},
{"learn":[0.08688296138],"iteration":473,"passed_time":2.500009431,"remaining_time":2.774272069},
{"learn":[0.0867059196],"iteration":474,"passed_time":2.504408487,"remaining_time":2.768030433},
{"learn":[0.08655758513],"iteration":475,"passed_time":2.508866294,"remaining_time":2.761861215},
{"learn":[0.08640590212],"iteration":476,"passed_time":2.513593315,"remaining_time":2.755994347},
{"learn":[0.08627043993],"iteration":477,"passed_time":2.518133448,"remaining_time":2.749928159},
{"learn":[0.08608041462],"iteration":478,"passed_time":2.522777186,"remaining_time":2.743981031},
{"learn":[0.08593719121],"iteration":479,"passed_time":2.527299571,"remaining_time":2.737907868},
{"learn":[0.08584281155],"iteration":480,"passed_time":2.531886408,"remaining_time":2.731910698},
{"learn":[0.08568399949],"iteration":481,"passed_time":2.536243721,"remaining_time":2.725672712},
{"learn":[0.08552786187],"iteration":482,"passed_time":2.540578359,"remaining_time":2.719418243},
{"learn":[0.08540387998],"iteration":483,"passed_time":2.545033469,"remaining_time":2.713300144},
{"learn":[0.08526378448],"iteration":484,"passed_time":2.550154014,"remaining_time":2.707895499},
{"learn":[0.08517075951],"iteration":485,"passed_time":2.554629329,"remaining_time":2.70180962},
{"learn":[0.08506050047],"iteration":486,"passed_time":2.558914775,"remaining_time":2.695530348},
{"learn":[0.08494625824],"iteration":487,"passed_time":2.563461235,"remaining_time":2.689533099},
{"learn":[0.08471664225],"iteration":488,"passed_time":2.56785685,"remaining_time":2.683384152},
{"learn":[0.08458681331],"iteration":489,"passed_time":2.572161881,"remaining_time":2.67714808},
{"learn":[0.08446165253],"iteration":490,"passed_time":2.576703508,"remaining_time":2.671165143},
{"learn":[0.08430221261],"iteration":491,"passed_time":2.581154731,"remaining_time":2.665094722},
{"learn":[0.08415380455],"iteration":492,"passed_time":2.585650002,"remaining_time":2.659076169},
{"learn":[0.0840343005],"iteration":493,"passed_time":2.590371451,"remaining_time":2.653295454},
{"learn":[0.08391921444],"iteration":494,"passed_time":2.59561508,"remaining_time":2.648051748},
{"learn":[0.08378984023],"iteration":495,"passed_time":2.600218014,"remaining_time":2.642157015},
{"learn":[0.08362207669],"iteration":496,"passed_time":2.604532727,"remaining_time":2.635975778},
{"learn":[0.08356131844],"iteration":497,"passed_time":2.608886252,"remaining_time":2.629841161},
{"learn":[0.0834499644],"iteration":498,"passed_time":2.613365225,"remaining_time":2.623839634},
{"learn":[0.08337378545],"iteration":499,"passed_time":2.617799755,"remaining_time":2.617799755},
{"learn":[0.08332284736],"iteration":500,"passed_time":2.622101213,"remaining_time":2.611633744},
{"learn":[0.08320373896],"iteration":501,"passed_time":2.626435115,"remaining_time":2.605507345},
{"learn":[0.08305105399],"iteration":502,"passed_time":2.630998805,"remaining_time":2.599615121},
{"learn":[0.08298832564],"iteration":503,"passed_time":2.63573868,"remaining_time":2.593901558},
{"learn":[0.08283153532],"iteration":504,"passed_time":2.640085776,"remaining_time":2.58780685},
{"learn":[0.08268540058],"iteration":505,"passed_time":2.64457726,"remaining_time":2.581860012},
{"learn":[0.08251842224],"iteration":506,"passed_time":2.649286019,"remaining_time":2.576130192},
{"learn":[0.08241847374],"iteration":507,"passed_time":2.653576947,"remaining_time":2.56999972},
{"learn":[0.08229505346],"iteration":508,"passed_time":2.658035515,"remaining_time":2.564038188},
{"learn":[0.08214708099],"iteration":509,"passed_time":2.662616446,"remaining_time":2.558200115},
{"learn":[0.08204605352],"iteration":510,"passed_time":2.667382602,"remaining_time":2.552544213},
{"learn":[0.08196417606],"iteration":511,"passed_time":2.672308401,"remaining_time":2.547043945},
{"learn":[0.08185354413],"iteration":512,"passed_time":2.677032903,"remaining_time":2.541354822},
{"learn":[0.08170121856],"iteration":513,"passed_time":2.681631643,"remaining_time":2.535550542},
{"learn":[0.08162809009],"iteration":514,"passed_time":2.686329202,"remaining_time":2.529844006},
{"learn":[0.08154743246],"iteration":515,"passed_time":2.690840967,"remaining_time":2.523967109},
{"learn":[0.08138459296],"iteration":516,"passed_time":2.695384022,"remaining_time":2.518124725},
{"learn":[0.08122586951],"iteration":517,"passed_time":2.699828101,"remaining_time":2.51219526},
{"learn":[0.08108444589],"iteration":518,"passed_time":2.704132759,"remaining_time":2.506142306},
{"learn":[0.08095770238],"iteration":519,"passed_time":2.708465569,"remaining_time":2.500122063},
{"learn":[0.08075355612],"iteration":520,"passed_time":2.713478313,"remaining_time":2.49473342},
{"learn":[0.08062613194],"iteration":521,"passed_time":2.717804472,"remaining_time":2.488717505},
{"learn":[0.08050077762],"iteration":522,"passed_time":2.722044905,"remaining_time":2.482629866},
{"learn":[0.08032647616],"iteration":523,"passed_time":2.726500984,"remaining_time":2.476745169},
{"learn":[0.08016964112],"iteration":524,"passed_time":2.731182667,"remaining_time":2.471070032},
{"learn":[0.0800526667],"iteration":525,"passed_time":2.736066034,"remaining_time":2.465580419},
{"learn":[0.07995700217],"iteration":526,"passed_time":2.740415421,"remaining_time":2.459613841},
{"learn":[0.07983493997],"iteration":527,"passed_time":2.744683534,"remaining_time":2.453580735},
{"learn":[0.07965251842],"iteration":528,"passed_time":2.749060595,"remaining_time":2.447651305},
{"learn":[0.07957612342],"iteration":529,"passed_time":2.753498402,"remaining_time":2.441781602},
{"learn":[0.07948554744],"iteration":530,"passed_time":2.757858844,"remaining_time":2.43584896},
{"learn":[0.07931485892],"iteration":531,"passed_time":2.762294316,"remaining_time":2.429988233},
{"learn":[0.07919400199],"iteration":532,"passed_time":2.766760803,"remaining_time":2.424160028},
{"learn":[0.0789537205],"iteration":533,"passed_time":2.77129849,"remaining_time":2.418399056},
{"learn":[0.07885420772],"iteration":534,"passed_time":2.775729439,"remaining_time":2.412549886},
{"learn":[0.07873272136],"iteration":535,"passed_time":2.780029856,"remaining_time":2.40659301},
{"learn":[0.07866162488],"iteration":536,"passed_time":2.784486335,"remaining_time":2.400776858},
{"learn":[0.07853490792],"iteration":537,"passed_time":2.789061563,"remaining_time":2.395067736},
{"learn":[0.07844916607],"iteration":538,"passed_time":2.793340431,"remaining_time":2.389109348},
{"learn":[0.07834962883],"iteration":539,"passed_time":2.797632238,"remaining_time":2.383168203},
{"learn":[0.07816298707],"iteration":540,"passed_time":2.80214555,"remaining_time":2.377421085},
{"learn":[0.07807495905],"iteration":541,"passed_time":2.806488354,"remaining_time":2.371534439},
{"learn":[0.07791241295],"iteration":542,"passed_time":2.810819872,"remaining_time":2.36564398},
{"learn":[0.07777181078],"iteration":543,"passed_time":2.815324049,"remaining_time":2.359903983},
{"learn":[0.07765990024],"iteration":544,"passed_time":2.819888756,"remaining_time":2.354219054},
{"learn":[0.07750153548],"iteration":545,"passed_time":2.836132619,"remaining_time":2.358249467},
{"learn":[0.07738362635],"iteration":546,"passed_time":2.8546561,"remaining_time":2.364093625},
{"learn":[0.07727643844],"iteration":547,"passed_time":2.868458207,"remaining_time":2.365954579},
{"learn":[0.07713696871],"iteration":548,"passed_time":2.881437166,"remaining_time":2.367082262},
{"learn":[0.07701770202],"iteration":549,"passed_time":2.894545269,"remaining_time":2.368264311},
{"learn":[0.07687357722],"iteration":550,"passed_time":2.907347416,"remaining_time":2.369145172},
{"learn":[0.07679073857],"iteration":551,"passed_time":2.917738865,"remaining_time":2.368019948},
{"learn":[0.07668254731],"iteration":552,"passed_time":2.927007303,"remaining_time":2.365953462},
{"learn":[0.07655610606],"iteration":553,"passed_time":2.934361139,"remaining_time":2.362319617},
{"learn":[0.07645161819],"iteration":554,"passed_time":2.968913167,"remaining_time":2.380479926},
{"learn":[0.07631286241],"iteration":555,"passed_time":2.983766556,"remaining_time":2.382720056},
{"learn":[0.07620094529],"iteration":556,"passed_time":2.997365643,"remaining_time":2.38390122},
{"learn":[0.07609779108],"iteration":557,"passed_time":3.010795348,"remaining_time":2.38489524},
{"learn":[0.0759835641],"iteration":558,"passed_time":3.024676981,"remaining_time":2.386194183},
{"learn":[0.07584560371],"iteration":559,"passed_time":3.03661847,"remaining_time":2.385914512},
{"learn":[0.0757393137],"iteration":560,"passed_time":3.045779079,"remaining_time":2.38341714},
{"learn":[0.07563166118],"iteration":561,"passed_time":3.055137727,"remaining_time":2.381050399},
{"learn":[0.07550277337],"iteration":562,"passed_time":3.064366139,"remaining_time":2.378557731},
{"learn":[0.07541745244],"iteration":563,"passed_time":3.074900005,"remaining_time":2.377050358},
{"learn":[0.07534253304],"iteration":564,"passed_time":3.082177932,"remaining_time":2.373004249},
{"learn":[0.07522527429],"iteration":565,"passed_time":3.089283608,"remaining_time":2.36881464},
{"learn":[0.07498873395],"iteration":566,"passed_time":3.096488375,"remaining_time":2.364690417},
{"learn":[0.07486312045],"iteration":567,"passed_time":3.1107525,"remaining_time":2.365924437},
{"learn":[0.07479073232],"iteration":568,"passed_time":3.124091409,"remaining_time":2.366403159},
{"learn":[0.07467830031],"iteration":569,"passed_time":3.137005078,"remaining_time":2.366512603},
{"learn":[0.07455792003],"iteration":570,"passed_time":3.149923367,"remaining_time":2.366579903},
{"learn":[0.07440085579],"iteration":571,"passed_time":3.162802488,"remaining_time":2.366572491},
{"learn":[0.07432183226],"iteration":572,"passed_time":3.175849102,"remaining_time":2.366644968},
{"learn":[0.07422412047],"iteration":573,"passed_time":3.188844232,"remaining_time":2.366633524},
{"learn":[0.07401559723],"iteration":574,"passed_time":3.201815251,"remaining_time":2.366559099},
{"learn":[0.0739371059],"iteration":575,"passed_time":3.213713833,"remaining_time":2.36565046},
{"learn":[0.07382875953],"iteration":576,"passed_time":3.225308707,"remaining_time":2.36448108},
{"learn":[0.07375920509],"iteration":577,"passed_time":3.237152489,"remaining_time":2.363457354},
{"learn":[0.07361676175],"iteration":578,"passed_time":3.248941488,"remaining_time":2.362356418},
{"learn":[0.07351557432],"iteration":579,"passed_time":3.26487151,"remaining_time":2.3642173},
{"learn":[0.07331803264],"iteration":580,"passed_time":3.280761262,"remaining_time":2.365987898},
{"learn":[0.07324346693],"iteration":581,"passed_time":3.292967418,"remaining_time":2.365052201},
{"learn":[0.07313769516],"iteration":582,"passed_time":3.30173354,"remaining_time":2.3616173},
{"learn":[0.07301612382],"iteration":583,"passed_time":3.310230693,"remaining_time":2.357972548},
{"learn":[0.07290711853],"iteration":584,"passed_time":3.318700959,"remaining_time":2.354292133},
{"learn":[0.07274764306],"iteration":585,"passed_time":3.327338062,"remaining_time":2.350713238},
{"learn":[0.0725951069],"iteration":586,"passed_time":3.336125615,"remaining_time":2.347222962},
{"learn":[0.07249469253],"iteration":587,"passed_time":3.345017809,"remaining_time":2.343787989},
{"learn":[0.07242627491],"iteration":588,"passed_time":3.35355471,"remaining_time":2.340086563},
{"learn":[0.07226155311],"iteration":589,"passed_time":3.362337796,"remaining_time":2.336539824},
{"learn":[0.07215484552],"iteration":590,"passed_time":3.370903789,"remaining_time":2.332825127},
{"learn":[0.07204619621],"iteration":591,"passed_time":3.379316208,"remaining_time":2.328988197},
{"learn":[0.07194242357],"iteration":592,"passed_time":3.387985666,"remaining_time":2.325312253},
{"learn":[0.07187679544],"iteration":593,"passed_time":3.396591287,"remaining_time":2.321575863},
{"learn":[0.07169801917],"iteration":594,"passed_time":3.405662402,"remaining_time":2.318139954},
{"learn":[0.07156121258],"iteration":595,"passed_time":3.414231164,"remaining_time":2.314344615},
{"learn":[0.07146287514],"iteration":596,"passed_time":3.423038609,"remaining_time":2.310694404},
{"learn":[0.07133773518],"iteration":597,"passed_time":3.431565933,"remaining_time":2.306838637},
{"learn":[0.07129033616],"iteration":598,"passed_time":3.440084488,"remaining_time":2.302961402},
{"learn":[0.07120969924],"iteration":599,"passed_time":3.448628687,"remaining_time":2.299085791},
{"learn":[0.07109624403],"iteration":600,"passed_time":3.457242724,"remaining_time":2.29524101},
{"learn":[0.07098684529],"iteration":601,"passed_time":3.465661132,"remaining_time":2.291251048},
{"learn":[0.07090879148],"iteration":602,"passed_time":3.474194233,"remaining_time":2.287321908},
{"learn":[0.07078742212],"iteration":603,"passed_time":3.482692024,"remaining_time":2.283354373},
{"learn":[0.07054880834],"iteration":604,"passed_time":3.491494695,"remaining_time":2.279570917},
{"learn":[0.07040621434],"iteration":605,"passed_time":3.500232174,"remaining_time":2.275728509},
{"learn":[0.07028655807],"iteration":606,"passed_time":3.509825297,"remaining_time":2.272423957},
{"learn":[0.07019553832],"iteration":607,"passed_time":3.518734966,"remaining_time":2.26865807},
{"learn":[0.07009543669],"iteration":608,"passed_time":3.527723218,"remaining_time":2.264925744},
{"learn":[0.06998887792],"iteration":609,"passed_time":3.536392717,"remaining_time":2.260972393},
{"learn":[0.06993253166],"iteration":610,"passed_time":3.545383908,"remaining_time":2.257208413},
{"learn":[0.06989233496],"iteration":611,"passed_time":3.553902018,"remaining_time":2.253127423},
{"learn":[0.06978902224],"iteration":612,"passed_time":3.562403759,"remaining_time":2.249021623},
{"learn":[0.06972794831],"iteration":613,"passed_time":3.570780659,"remaining_time":2.24482302},
{"learn":[0.06965123007],"iteration":614,"passed_time":3.579457811,"remaining_time":2.240798792},
{"learn":[0.06956179943],"iteration":615,"passed_time":3.58771487,"remaining_time":2.236497581},
{"learn":[0.06945784689],"iteration":616,"passed_time":3.596414014,"remaining_time":2.23245797},
{"learn":[0.06939937245],"iteration":617,"passed_time":3.605015053,"remaining_time":2.228342638},
{"learn":[0.06932559471],"iteration":618,"passed_time":3.612600365,"remaining_time":2.223587623},
{"learn":[0.06917750702],"iteration":619,"passed_time":3.619592318,"remaining_time":2.218459808},
{"learn":[0.06902542135],"iteration":620,"passed_time":3.626482302,"remaining_time":2.213263756},
{"learn":[0.06887884884],"iteration":621,"passed_time":3.633898727,"remaining_time":2.208382185},
{"learn":[0.06865894662],"iteration":622,"passed_time":3.640933952,"remaining_time":2.203261798},
{"learn":[0.06860378582],"iteration":623,"passed_time":3.647651377,"remaining_time":2.197943778},
{"learn":[0.06848635696],"iteration":624,"passed_time":3.654903008,"remaining_time":2.192941805},
{"learn":[0.06837428311],"iteration":625,"passed_time":3.662911179,"remaining_time":2.188384634},
{"learn":[0.06829282949],"iteration":626,"passed_time":3.66833457,"remaining_time":2.182278779},
{"learn":[0.0682207006],"iteration":627,"passed_time":3.673744132,"remaining_time":2.176166906},
{"learn":[0.06811236522],"iteration":628,"passed_time":3.678942357,"remaining_time":2.169932614},
{"learn":[0.06796374237],"iteration":629,"passed_time":3.68433943,"remaining_time":2.163818395},
{"learn":[0.06782023254],"iteration":630,"passed_time":3.689633335,"remaining_time":2.157646118},
{"learn":[0.06773164878],"iteration":631,"passed_time":3.695014168,"remaining_time":2.151527237},
{"learn":[0.06760743022],"iteration":632,"passed_time":3.700269322,"remaining_time":2.145337822},
{"learn":[0.06751804621],"iteration":633,"passed_time":3.705755151,"remaining_time":2.139284519},
{"learn":[0.06747761366],"iteration":634,"passed_time":3.711446637,"remaining_time":2.133351216},
{"learn":[0.06736198891],"iteration":635,"passed_time":3.71668594,"remaining_time":2.127159878},
{"learn":[0.06729364713],"iteration":636,"passed_time":3.721928068,"remaining_time":2.120973137},
{"learn":[0.06721890544],"iteration":637,"passed_time":3.727482154,"remaining_time":2.114966363},
{"learn":[0.06715649643],"iteration":638,"passed_time":3.732661886,"remaining_time":2.108749516},
{"learn":[0.06707005755],"iteration":639,"passed_time":3.737977797,"remaining_time":2.102612511},
{"learn":[0.06693795545],"iteration":640,"passed_time":3.743364071,"remaining_time":2.096517475},
{"learn":[0.06685113341],"iteration":641,"passed_time":3.748788219,"remaining_time":2.090445767},
{"learn":[0.06674144188],"iteration":642,"passed_time":3.754217604,"remaining_time":2.084378981},
{"learn":[0.06666708289],"iteration":643,"passed_time":3.759570102,"remaining_time":2.078271671},
{"learn":[0.06657777555],"iteration":644,"passed_time":3.764804243,"remaining_time":2.07210156},
{"learn":[0.06647191842],"iteration":645,"passed_time":3.770113233,"remaining_time":2.065975363},
{"learn":[0.06637078997],"iteration":646,"passed_time":3.775411172,"remaining_time":2.059845663},
{"learn":[0.06628528531],"iteration":647,"passed_time":3.780777095,"remaining_time":2.053755459},
{"learn":[0.0662019465],"iteration":648,"passed_time":3.786175433,"remaining_time":2.047685019},
{"learn":[0.06612737978],"iteration":649,"passed_time":3.792064466,"remaining_time":2.041880866},
{"learn":[0.06600088427],"iteration":650,"passed_time":3.797426496,"remaining_time":2.035793928},
{"learn":[0.06589463597],"iteration":651,"passed_time":3.802710104,"remaining_time":2.029667356},
{"learn":[0.06573304959],"iteration":652,"passed_time":3.808261956,"remaining_time":2.023685909},
{"learn":[0.06557017103],"iteration":653,"passed_time":3.813734283,"remaining_time":2.017663703},
{"learn":[0.06547587548],"iteration":654,"passed_time":3.818908832,"remaining_time":2.011486331},
{"learn":[0.06541579377],"iteration":655,"passed_time":3.82433605,"remaining_time":2.005444514},
{"learn":[0.06533721464],"iteration":656,"passed_time":3.829650751,"remaining_time":1.999345826},
{"learn":[0.06519966439],"iteration":657,"passed_time":3.8349731,"remaining_time":1.993253496},
{"learn":[0.06510041172],"iteration":658,"passed_time":3.840362529,"remaining_time":1.987198213},
{"learn":[0.06499095001],"iteration":659,"passed_time":3.845841081,"remaining_time":1.98119086},
{"learn":[0.06490331947],"iteration":660,"passed_time":3.851025906,"remaining_time":1.975034466},
{"learn":[0.06480462171],"iteration":661,"passed_time":3.85655109,"remaining_time":1.969054786},
{"learn":[0.06470412847],"iteration":662,"passed_time":3.862167725,"remaining_time":1.963122961},
{"learn":[0.06459126266],"iteration":663,"passed_time":3.867515852,"remaining_time":1.957056214},
{"learn":[0.06453496812],"iteration":664,"passed_time":3.87282259,"remaining_time":1.950970778},
{"learn":[0.06443047054],"iteration":665,"passed_time":3.878665075,"remaining_time":1.945156359},
{"learn":[0.06432291618],"iteration":666,"passed_time":3.883976316,"remaining_time":1.939076631},
{"learn":[0.06424105038],"iteration":667,"passed_time":3.889314445,"remaining_time":1.933012569},
{"learn":[0.06416565395],"iteration":668,"passed_time":3.894637547,"remaining_time":1.926943241},
{"learn":[0.06405461147],"iteration":669,"passed_time":3.900141339,"remaining_time":1.920965137},
{"learn":[0.06393339577],"iteration":670,"passed_time":3.905569047,"remaining_time":1.914951142},
{"learn":[0.06380154872],"iteration":671,"passed_time":3.911119193,"remaining_time":1.908998654},
{"learn":[0.06371961306],"iteration":672,"passed_time":3.916422581,"remaining_time":1.902927465},
{"learn":[0.06365702683],"iteration":673,"passed_time":3.92186849,"remaining_time":1.896927489},
{"learn":[0.06354911889],"iteration":674,"passed_time":3.926967862,"remaining_time":1.890762304},
{"learn":[0.06344103244],"iteration":675,"passed_time":3.931494891,"remaining_time":1.884325954},
{"learn":[0.06331045359],"iteration":676,"passed_time":3.936121416,"remaining_time":1.877942714},
{"learn":[0.0632352449],"iteration":677,"passed_time":3.940716024,"remaining_time":1.871549498},
{"learn":[0.06316505226],"iteration":678,"passed_time":3.945304928,"remaining_time":1.865158883},
{"learn":[0.06304379536],"iteration":679,"passed_time":3.949828755,"remaining_time":1.858742944},
{"learn":[0.06292781385],"iteration":680,"passed_time":3.954459087,"remaining_time":1.85238245},
{"learn":[0.06287323204],"iteration":681,"passed_time":3.959206633,"remaining_time":1.846081685},
{"learn":[0.06280549094],"iteration":682,"passed_time":3.963733457,"remaining_time":1.839683024},
{"learn":[0.0627105842],"iteration":683,"passed_time":3.995350455,"remaining_time":1.845805181},
{"learn":[0.06255481318],"iteration":684,"passed_time":4.009999596,"remaining_time":1.844014413},
{"learn":[0.06243226678],"iteration":685,"passed_time":4.0243532,"remaining_time":1.842050882},
{"learn":[0.06232511786],"iteration":686,"passed_time":4.039620629,"remaining_time":1.840467623},
{"learn":[0.06218918801],"iteration":687,"passed_time":4.0605107,"remaining_time":1.841394387},
{"learn":[0.06212177315],"iteration":688,"passed_time":4.075148318,"remaining_time":1.839435598},
{"learn":[0.06202737017],"iteration":689,"passed_time":4.088060653,"remaining_time":1.836664931},
{"learn":[0.06194380147],"iteration":690,"passed_time":4.101144231,"remaining_time":1.833941487},
{"learn":[0.06186631642],"iteration":691,"passed_time":4.114039598,"remaining_time":1.83110433},
{"learn":[0.06175846065],"iteration":692,"passed_time":4.126932854,"remaining_time":1.82823721},
{"learn":[0.06168708156],"iteration":693,"passed_time":4.134435354,"remaining_time":1.822964291},
{"learn":[0.06160600763],"iteration":694,"passed_time":4.148096281,"remaining_time":1.820387577},
{"learn":[0.06150330458],"iteration":695,"passed_time":4.16157763,"remaining_time":1.817700574},
{"learn":[0.06144170501],"iteration":696,"passed_time":4.174481047,"remaining_time":1.814731359},
{"learn":[0.06136753657],"iteration":697,"passed_time":4.18868247,"remaining_time":1.812295281},
{"learn":[0.0612969477],"iteration":698,"passed_time":4.201503887,"remaining_time":1.809231288},
{"learn":[0.06114762796],"iteration":699,"passed_time":4.214635217,"remaining_time":1.806272236},
{"learn":[0.06103514235],"iteration":700,"passed_time":4.232317219,"remaining_time":1.805225176},
{"learn":[0.06093418113],"iteration":701,"passed_time":4.243272214,"remaining_time":1.801275099},
{"learn":[0.06085796678],"iteration":702,"passed_time":4.251362548,"remaining_time":1.796094846},
{"learn":[0.0607764678],"iteration":703,"passed_time":4.259661015,"remaining_time":1.790993836},
{"learn":[0.0606506414],"iteration":704,"passed_time":4.265649108,"remaining_time":1.784917002},
{"learn":[0.0604977618],"iteration":705,"passed_time":4.271380278,"remaining_time":1.77873343},
{"learn":[0.06040600781],"iteration":706,"passed_time":4.277108963,"remaining_time":1.772550108},
{"learn":[0.06031108206],"iteration":707,"passed_time":4.282221843,"remaining_time":1.766114093},
{"learn":[0.06021050261],"iteration":708,"passed_time":4.286948555,"remaining_time":1.759523314},
{"learn":[0.06014750604],"iteration":709,"passed_time":4.29167875,"remaining_time":1.752939208},
{"learn":[0.06007378406],"iteration":710,"passed_time":4.29691131,"remaining_time":1.746564513},
{"learn":[0.05998627092],"iteration":711,"passed_time":4.301798769,"remaining_time":1.740053435},
{"learn":[0.05992510089],"iteration":712,"passed_time":4.306532061,"remaining_time":1.733484855},
{"learn":[0.05985998264],"iteration":713,"passed_time":4.311256141,"remaining_time":1.726917726},
{"learn":[0.05978427874],"iteration":714,"passed_time":4.31625959,"remaining_time":1.720467109},
{"learn":[0.05966739054],"iteration":715,"passed_time":4.320899303,"remaining_time":1.71387626},
{"learn":[0.05960655549],"iteration":716,"passed_time":4.325745494,"remaining_time":1.70737235},
{"learn":[0.05954534876],"iteration":717,"passed_time":4.330600336,"remaining_time":1.700876455},
{"learn":[0.05949514557],"iteration":718,"passed_time":4.336058013,"remaining_time":1.694620726},
{"learn":[0.05939696166],"iteration":719,"passed_time":4.340517713,"remaining_time":1.687979111},
{"learn":[0.05932469343],"iteration":720,"passed_time":4.34495717,"remaining_time":1.681335715},
{"learn":[0.05927566625],"iteration":721,"passed_time":4.349260639,"remaining_time":1.674646063},
{"learn":[0.05918058311],"iteration":722,"passed_time":4.353681014,"remaining_time":1.668007802},
{"learn":[0.05907413086],"iteration":723,"passed_time":4.358061954,"remaining_time":1.661360634},
{"learn":[0.05899860712],"iteration":724,"passed_time":4.36235427,"remaining_time":1.654686102},
{"learn":[0.05892375517],"iteration":725,"passed_time":4.366747035,"remaining_time":1.648056044},
{"learn":[0.05887802503],"iteration":726,"passed_time":4.371214969,"remaining_time":1.641460367},
{"learn":[0.05880611478],"iteration":727,"passed_time":4.375532491,"remaining_time":1.634814337},
{"learn":[0.05871660455],"iteration":728,"passed_time":4.379880897,"remaining_time":1.628186177},
{"learn":[0.05866068909],"iteration":729,"passed_time":4.384311905,"remaining_time":1.621594814},
{"learn":[0.05862197542],"iteration":730,"passed_time":4.388743085,"remaining_time":1.615009425},
{"learn":[0.05856456564],"iteration":731,"passed_time":4.393159736,"remaining_time":1.608424603},
{"learn":[0.05849608535],"iteration":732,"passed_time":4.397397371,"remaining_time":1.601780488},
{"learn":[0.0583973383],"iteration":733,"passed_time":4.401798917,"remaining_time":1.595202332},
{"learn":[0.05813804213],"iteration":734,"passed_time":4.406215014,"remaining_time":1.588635345},
{"learn":[0.05806826185],"iteration":735,"passed_time":4.410625117,"remaining_time":1.582072053},
{"learn":[0.05795698314],"iteration":736,"passed_time":4.415017527,"remaining_time":1.57550829},
{"learn":[0.05790794126],"iteration":737,"passed_time":4.419589593,"remaining_time":1.569014191},
{"learn":[0.05781353843],"iteration":738,"passed_time":4.423991743,"remaining_time":1.562465284},
{"learn":[0.05773992026],"iteration":739,"passed_time":4.428300771,"remaining_time":1.55588946},
{"learn":[0.05764940602],"iteration":740,"passed_time":4.433221059,"remaining_time":1.549533407},
{"learn":[0.05756113209],"iteration":741,"passed_time":4.440608295,"remaining_time":1.544039003},
{"learn":[0.05748125399],"iteration":742,"passed_time":4.445476738,"remaining_time":1.537668266},
{"learn":[0.05741760863],"iteration":743,"passed_time":4.450669281,"remaining_time":1.531413086},
{"learn":[0.05730640146],"iteration":744,"passed_time":4.45497795,"remaining_time":1.524858224},
{"learn":[0.05719769883],"iteration":745,"passed_time":4.459507118,"remaining_time":1.518384461},
{"learn":[0.0571327279],"iteration":746,"passed_time":4.464021051,"remaining_time":1.511910744},
{"learn":[0.05706538852],"iteration":747,"passed_time":4.469118616,"remaining_time":1.505638892},
{"learn":[0.05698812729],"iteration":748,"passed_time":4.474109809,"remaining_time":1.499334529},
{"learn":[0.05691693057],"iteration":749,"passed_time":4.478754686,"remaining_time":1.492918229},
{"learn":[0.05683235976],"iteration":750,"passed_time":4.484139543,"remaining_time":1.486751992},
{"learn":[0.05669887346],"iteration":751,"passed_time":4.488731614,"remaining_time":1.480326383},
{"learn":[0.05660602314],"iteration":752,"passed_time":4.493610022,"remaining_time":1.473999569},
{"learn":[0.0564956105],"iteration":753,"passed_time":4.498336504,"remaining_time":1.467627029},
{"learn":[0.05638280721],"iteration":754,"passed_time":4.503471719,"remaining_time":1.461391485},
{"learn":[0.05629547403],"iteration":755,"passed_time":4.508358195,"remaining_time":1.455078571},
{"learn":[0.05619836566],"iteration":756,"passed_time":4.513040024,"remaining_time":1.448703733},
{"learn":[0.05614606393],"iteration":757,"passed_time":4.517718096,"remaining_time":1.442332163},
{"learn":[0.05610211146],"iteration":758,"passed_time":4.522572327,"remaining_time":1.436020989},
{"learn":[0.0560367349],"iteration":759,"passed_time":4.527291458,"remaining_time":1.429670987},
{"learn":[0.05597447984],"iteration":760,"passed_time":4.5319471,"remaining_time":1.423305331},
{"learn":[0.05592372436],"iteration":761,"passed_time":4.537078204,"remaining_time":1.417092667},
{"learn":[0.05589104181],"iteration":762,"passed_time":4.541900523,"remaining_time":1.410786925},
{"learn":[0.0558253042],"iteration":763,"passed_time":4.546665837,"remaining_time":1.404467458},
{"learn":[0.05575119164],"iteration":764,"passed_time":4.551554915,"remaining_time":1.398190072},
{"learn":[0.05570562466],"iteration":765,"passed_time":4.556308999,"remaining_time":1.391875073},
{"learn":[0.05562274489],"iteration":766,"passed_time":4.561017351,"remaining_time":1.385550251},
{"learn":[0.05552618495],"iteration":767,"passed_time":4.565672608,"remaining_time":1.3792136},
{"learn":[0.05548815278],"iteration":768,"passed_time":4.570384014,"remaining_time":1.372898189},
{"learn":[0.05538889212],"iteration":769,"passed_time":4.575132355,"remaining_time":1.366597976},
{"learn":[0.05534902746],"iteration":770,"passed_time":4.579714473,"remaining_time":1.360252418},
{"learn":[0.05527751595],"iteration":771,"passed_time":4.584685942,"remaining_time":1.354026418},
{"learn":[0.05521005535],"iteration":772,"passed_time":4.589325689,"remaining_time":1.34770625},
{"learn":[0.05515191578],"iteration":773,"passed_time":4.594042177,"remaining_time":1.341412832},
{"learn":[0.05501982155],"iteration":774,"passed_time":4.598771787,"remaining_time":1.335127293},
{"learn":[0.05495110098],"iteration":775,"passed_time":4.60319121,"remaining_time":1.328756226},
{"learn":[0.05492096195],"iteration":776,"passed_time":4.607581373,"remaining_time":1.322381784},
{"learn":[0.0548726538],"iteration":777,"passed_time":4.611900759,"remaining_time":1.315992247},
{"learn":[0.05480622432],"iteration":778,"passed_time":4.61697804,"remaining_time":1.309823038},
{"learn":[0.05471843408],"iteration":779,"passed_time":4.621549347,"remaining_time":1.303513918},
{"learn":[0.05459052601],"iteration":780,"passed_time":4.626131732,"remaining_time":1.297212355},
{"learn":[0.05454994529],"iteration":781,"passed_time":4.630738686,"remaining_time":1.290922038},
{"learn":[0.054494452],"iteration":782,"passed_time":4.635773407,"remaining_time":1.284754571},
{"learn":[0.05444973523],"iteration":783,"passed_time":4.640345473,"remaining_time":1.278462528},
{"learn":[0.05435521615],"iteration":784,"passed_time":4.644919822,"remaining_time":1.272175493},
{"learn":[0.05426904315],"iteration":785,"passed_time":4.649408159,"remaining_time":1.265869397},
{"learn":[0.05418023363],"iteration":786,"passed_time":4.654081968,"remaining_time":1.259618118},
{"learn":[0.05414831427],"iteration":787,"passed_time":4.658621793,"remaining_time":1.253334797},
{"learn":[0.05406602889],"iteration":788,"passed_time":4.663040701,"remaining_time":1.247023559},
{"learn":[0.05397375735],"iteration":789,"passed_time":4.667649857,"remaining_time":1.240767684},
{"learn":[0.05389027661],"iteration":790,"passed_time":4.672068977,"remaining_time":1.23446576},
{"learn":[0.05379468268],"iteration":791,"passed_time":4.676440882,"remaining_time":1.228156191},
{"learn":[0.05371490316],"iteration":792,"passed_time":4.680780008,"remaining_time":1.221842953},
{"learn":[0.05365590621],"iteration":793,"passed_time":4.685497263,"remaining_time":1.215632791},
{"learn":[0.05359060918],"iteration":794,"passed_time":4.690021856,"remaining_time":1.209376705},
{"learn":[0.05351209271],"iteration":795,"passed_time":4.694368338,"remaining_time":1.203079323},
{"learn":[0.05344495367],"iteration":796,"passed_time":4.69874487,"remaining_time":1.19679449},
{"learn":[0.05341081304],"iteration":797,"passed_time":4.703088376,"remaining_time":1.19050608},
{"learn":[0.05333847076],"iteration":798,"passed_time":4.707377598,"remaining_time":1.184208883},
{"learn":[0.05329621877],"iteration":799,"passed_time":4.711814165,"remaining_time":1.177953541},
{"learn":[0.0532578531],"iteration":800,"passed_time":4.716173029,"remaining_time":1.171683437},
{"learn":[0.05322715646],"iteration":801,"passed_time":4.720493524,"remaining_time":1.165408626},
{"learn":[0.0531429538],"iteration":802,"passed_time":4.724866692,"remaining_time":1.159151604},
{"learn":[0.05308187106],"iteration":803,"passed_time":4.729354874,"remaining_time":1.152927308},
{"learn":[0.05300732677],"iteration":804,"passed_time":4.733879859,"remaining_time":1.146716239},
{"learn":[0.05292975641],"iteration":805,"passed_time":4.738527615,"remaining_time":1.140538905},
{"learn":[0.05287427792],"iteration":806,"passed_time":4.742815035,"remaining_time":1.134279184},
{"learn":[0.05279963874],"iteration":807,"passed_time":4.747217921,"remaining_time":1.128051783},
{"learn":[0.05269657307],"iteration":808,"passed_time":4.751659743,"remaining_time":1.121838085},
{"learn":[0.05261210945],"iteration":809,"passed_time":4.756029763,"remaining_time":1.11561192},
{"learn":[0.05256712221],"iteration":810,"passed_time":4.760503828,"remaining_time":1.109414579},
{"learn":[0.05248778485],"iteration":811,"passed_time":4.764959723,"remaining_time":1.103217276},
{"learn":[0.05239206398],"iteration":812,"passed_time":4.769256594,"remaining_time":1.096987679},
{"learn":[0.05232281842],"iteration":813,"passed_time":4.773621557,"remaining_time":1.09077839},
{"learn":[0.05228739383],"iteration":814,"passed_time":4.778039225,"remaining_time":1.084585591},
{"learn":[0.05221158438],"iteration":815,"passed_time":4.782697508,"remaining_time":1.078451399},
{"learn":[0.05215407224],"iteration":816,"passed_time":4.787155403,"remaining_time":1.072275935},
{"learn":[0.05214311476],"iteration":817,"passed_time":4.791516612,"remaining_time":1.066083158},
{"learn":[0.05210313784],"iteration":818,"passed_time":4.796022295,"remaining_time":1.059926783},
{"learn":[0.05199831248],"iteration":819,"passed_time":4.800423638,"remaining_time":1.05375153},
{"learn":[0.05188204316],"iteration":820,"passed_time":4.804812025,"remaining_time":1.047577774},
{"learn":[0.05182995885],"iteration":821,"passed_time":4.809254073,"remaining_time":1.041419982},
{"learn":[0.05174489303],"iteration":822,"passed_time":4.813794885,"remaining_time":1.0352876},
{"learn":[0.05167213391],"iteration":823,"passed_time":4.818215409,"remaining_time":1.029133388},
{"learn":[0.05161764638],"iteration":824,"passed_time":4.822544494,"remaining_time":1.022963984},
{"learn":[0.05153835734],"iteration":825,"passed_time":4.827140333,"remaining_time":1.016855227},
{"learn":[0.05147628463],"iteration":826,"passed_time":4.83153286,"remaining_time":1.010707599},
{"learn":[0.05137434857],"iteration":827,"passed_time":4.836472873,"remaining_time":1.00467794},
{"learn":[0.05130208303],"iteration":828,"passed_time":4.840910219,"remaining_time":0.9985472225},
{"learn":[0.05117576759],"iteration":829,"passed_time":4.845320991,"remaining_time":0.9924151426},
{"learn":[0.05113640633],"iteration":830,"passed_time":4.849624714,"remaining_time":0.9862654353},
{"learn":[0.05102235431],"iteration":831,"passed_time":4.855021962,"remaining_time":0.9803409731},
{"learn":[0.05096779523],"iteration":832,"passed_time":4.859546186,"remaining_time":0.9742427527},
{"learn":[0.05090402905],"iteration":833,"passed_time":4.864147538,"remaining_time":0.9681636587},
{"learn":[0.05084678266],"iteration":834,"passed_time":4.870257417,"remaining_time":0.9623861961},
{"learn":[0.05078202693],"iteration":835,"passed_time":4.888595662,"remaining_time":0.9590068045},
{"learn":[0.05072145758],"iteration":836,"passed_time":4.893477539,"remaining_time":0.9529711337},
{"learn":[0.05062539299],"iteration":837,"passed_time":4.89838531,"remaining_time":0.9469432221},
{"learn":[0.05058509873],"iteration":838,"passed_time":4.903395796,"remaining_time":0.9409376915},
{"learn":[0.05053155723],"iteration":839,"passed_time":4.908297926,"remaining_time":0.9349138906},
{"learn":[0.05041876521],"iteration":840,"passed_time":4.913173647,"remaining_time":0.9288877643},
{"learn":[0.05035625716],"iteration":841,"passed_time":4.918317686,"remaining_time":0.9229147202},
{"learn":[0.05030395126],"iteration":842,"passed_time":4.922862282,"remaining_time":0.9168320028},
{"learn":[0.050293996],"iteration":843,"passed_time":4.927416666,"remaining_time":0.9107547392},
{"learn":[0.05025780757],"iteration":844,"passed_time":4.931921516,"remaining_time":0.9046719941},
{"learn":[0.05020397556],"iteration":845,"passed_time":4.93658424,"remaining_time":0.8986217175},
{"learn":[0.05015707019],"iteration":846,"passed_time":4.941194216,"remaining_time":0.892565189},
{"learn":[0.05009746777],"iteration":847,"passed_time":4.945608653,"remaining_time":0.8864770226},
{"learn":[0.05001655368],"iteration":848,"passed_time":4.950090456,"remaining_time":0.8804047807},
{"learn":[0.04995242218],"iteration":849,"passed_time":4.954661484,"remaining_time":0.8743520266},
{"learn":[0.04984002626],"iteration":850,"passed_time":4.959339042,"remaining_time":0.8683214069},
{"learn":[0.04977796162],"iteration":851,"passed_time":4.963769128,"remaining_time":0.8622509752},
{"learn":[0.04973375486],"iteration":852,"passed_time":4.968375581,"remaining_time":0.8562147835},
{"learn":[0.04970312486],"iteration":853,"passed_time":4.972959878,"remaining_time":0.8501781524},
{"learn":[0.04963924826],"iteration":854,"passed_time":4.977428456,"remaining_time":0.8441252937},
{"learn":[0.04956894075],"iteration":855,"passed_time":4.982146333,"remaining_time":0.8381180747},
{"learn":[0.04945715902],"iteration":856,"passed_time":4.987115806,"remaining_time":0.8321558462},
{"learn":[0.04943364745],"iteration":857,"passed_time":4.991688732,"remaining_time":0.826130303},
{"learn":[0.04936798647],"iteration":858,"passed_time":4.9962246,"remaining_time":0.8201020588},
{"learn":[0.04926427013],"iteration":859,"passed_time":5.000984183,"remaining_time":0.8141137042},
{"learn":[0.04919827034],"iteration":860,"passed_time":5.005725432,"remaining_time":0.808125244},
{"learn":[0.04913058537],"iteration":861,"passed_time":5.010268569,"remaining_time":0.8021079611},
{"learn":[0.04900912677],"iteration":862,"passed_time":5.014756892,"remaining_time":0.796085393},
{"learn":[0.04894378746],"iteration":863,"passed_time":5.020049227,"remaining_time":0.7901929338},
{"learn":[0.04883973835],"iteration":864,"passed_time":5.024720561,"remaining_time":0.7842049431},
{"learn":[0.04876453434],"iteration":865,"passed_time":5.029321608,"remaining_time":0.7782091171},
{"learn":[0.04873039238],"iteration":866,"passed_time":5.034157198,"remaining_time":0.7722524883},
{"learn":[0.0486401831],"iteration":867,"passed_time":5.038988523,"remaining_time":0.7662977938},
{"learn":[0.04855338415],"iteration":868,"passed_time":5.043454499,"remaining_time":0.7602906092},
{"learn":[0.04848912814],"iteration":869,"passed_time":5.048021689,"remaining_time":0.7543020915},
{"learn":[0.04845070997],"iteration":870,"passed_time":5.053164878,"remaining_time":0.7484021462},
{"learn":[0.048442496],"iteration":871,"passed_time":5.05761453,"remaining_time":0.7424021329},
{"learn":[0.04839485786],"iteration":872,"passed_time":5.062068929,"remaining_time":0.7364063619},
{"learn":[0.0482988363],"iteration":873,"passed_time":5.066585454,"remaining_time":0.7304230746},
{"learn":[0.048202905],"iteration":874,"passed_time":5.071278202,"remaining_time":0.7244683146},
{"learn":[0.0481582607],"iteration":875,"passed_time":5.075753121,"remaining_time":0.7184856016},
{"learn":[0.04812506235],"iteration":876,"passed_time":5.080521777,"remaining_time":0.7125475241},
{"learn":[0.04801984121],"iteration":877,"passed_time":5.085436222,"remaining_time":0.7066323679},
{"learn":[0.04797190772],"iteration":878,"passed_time":5.089759548,"remaining_time":0.7006381176},
{"learn":[0.04796126156],"iteration":879,"passed_time":5.094125635,"remaining_time":0.6946534957},
{"learn":[0.04786398198],"iteration":880,"passed_time":5.098537728,"remaining_time":0.6886787623},
{"learn":[0.04781228369],"iteration":881,"passed_time":5.102965475,"remaining_time":0.6827096668},
{"learn":[0.04777822987],"iteration":882,"passed_time":5.107431124,"remaining_time":0.6767490844},
{"learn":[0.04772250495],"iteration":883,"passed_time":5.111812282,"remaining_time":0.6707807972},
{"learn":[0.04764179338],"iteration":884,"passed_time":5.116335858,"remaining_time":0.6648346031},
{"learn":[0.04760487127],"iteration":885,"passed_time":5.12089584,"remaining_time":0.6588963045},
{"learn":[0.04753204728],"iteration":886,"passed_time":5.125464073,"remaining_time":0.6529621648},
{"learn":[0.04743146764],"iteration":887,"passed_time":5.129907206,"remaining_time":0.6470153233},
{"learn":[0.04742014026],"iteration":888,"passed_time":5.134574032,"remaining_time":0.6410997948},
{"learn":[0.04730899498],"iteration":889,"passed_time":5.138994513,"remaining_time":0.6351566252},
{"learn":[0.0472705991],"iteration":890,"passed_time":5.14342028,"remaining_time":0.6292175202},
{"learn":[0.04721576886],"iteration":891,"passed_time":5.147780578,"remaining_time":0.6232738816},
{"learn":[0.04718078842],"iteration":892,"passed_time":5.152145273,"remaining_time":0.617334316},
{"learn":[0.04716031972],"iteration":893,"passed_time":5.156521649,"remaining_time":0.6113996586},
{"learn":[0.04713879856],"iteration":894,"passed_time":5.160926837,"remaining_time":0.6054718635},
{"learn":[0.04705744786],"iteration":895,"passed_time":5.165252808,"remaining_time":0.5995382724},
{"learn":[0.04701350065],"iteration":896,"passed_time":5.169818066,"remaining_time":0.5936357422},
{"learn":[0.04694404336],"iteration":897,"passed_time":5.174176566,"remaining_time":0.5877127058},
{"learn":[0.04685343601],"iteration":898,"passed_time":5.178515482,"remaining_time":0.5817909496},
{"learn":[0.04680584493],"iteration":899,"passed_time":5.182832502,"remaining_time":0.575870278},
{"learn":[0.04678032131],"iteration":900,"passed_time":5.187324642,"remaining_time":0.5699724079},
{"learn":[0.04671922938],"iteration":901,"passed_time":5.191739431,"remaining_time":0.5640692509},
{"learn":[0.04666521201],"iteration":902,"passed_time":5.19602507,"remaining_time":0.5581555169},
{"learn":[0.04661370679],"iteration":903,"passed_time":5.200565999,"remaining_time":0.5522724954},
{"learn":[0.04656096051],"iteration":904,"passed_time":5.204977815,"remaining_time":0.5463788867},
{"learn":[0.0464633234],"iteration":905,"passed_time":5.209269812,"remaining_time":0.5404761174},
{"learn":[0.04637016713],"iteration":906,"passed_time":5.213647464,"remaining_time":0.5345856826},
{"learn":[0.04634404886],"iteration":907,"passed_time":5.218438495,"remaining_time":0.5287404642},
{"learn":[0.04631798043],"iteration":908,"passed_time":5.223910243,"remaining_time":0.5229657119},
{"learn":[0.04627997852],"iteration":909,"passed_time":5.228423542,"remaining_time":0.5170968339},
{"learn":[0.04620639411],"iteration":910,"passed_time":5.233035008,"remaining_time":0.5112405222},
{"learn":[0.04617656421],"iteration":911,"passed_time":5.238021732,"remaining_time":0.5054231495},
{"learn":[0.04613329974],"iteration":912,"passed_time":5.242565635,"remaining_time":0.4995654001},
{"learn":[0.0460623889],"iteration":913,"passed_time":5.247105412,"remaining_time":0.4937101372},
{"learn":[0.04601358219],"iteration":914,"passed_time":5.251687748,"remaining_time":0.4878617033},
{"learn":[0.04592321706],"iteration":915,"passed_time":5.256215951,"remaining_time":0.4820110697},
{"learn":[0.04586241391],"iteration":916,"passed_time":5.260759704,"remaining_time":0.4761647279},
{"learn":[0.04577394165],"iteration":917,"passed_time":5.265284282,"remaining_time":0.470319511},
{"learn":[0.04571408065],"iteration":918,"passed_time":5.271157184,"remaining_time":0.4645960086},
{"learn":[0.04564917128],"iteration":919,"passed_time":5.278100778,"remaining_time":0.458965285},
{"learn":[0.04560768554],"iteration":920,"passed_time":5.283333742,"remaining_time":0.453184979},
{"learn":[0.04558801074],"iteration":921,"passed_time":5.287982363,"remaining_time":0.4473564255},
{"learn":[0.0455608204],"iteration":922,"passed_time":5.29261594,"remaining_time":0.4415291738},
{"learn":[0.04550863174],"iteration":923,"passed_time":5.29721637,"remaining_time":0.4357017793},
{"learn":[0.04544344011],"iteration":924,"passed_time":5.301857498,"remaining_time":0.4298803376},
{"learn":[0.0454007877],"iteration":925,"passed_time":5.306541251,"remaining_time":0.4240648516},
{"learn":[0.04536264757],"iteration":926,"passed_time":5.311033578,"remaining_time":0.4182367327},
{"learn":[0.04533800226],"iteration":927,"passed_time":5.315452524,"remaining_time":0.4124057993},
{"learn":[0.04527837761],"iteration":928,"passed_time":5.320113506,"remaining_time":0.4065964036},
{"learn":[0.0451840684],"iteration":929,"passed_time":5.324686723,"remaining_time":0.4007828716},
{"learn":[0.04510033155],"iteration":930,"passed_time":5.329365596,"remaining_time":0.3949798347},
{"learn":[0.04503088465],"iteration":931,"passed_time":5.333993643,"remaining_time":0.3891755019},
{"learn":[0.04500404128],"iteration":932,"passed_time":5.338856435,"remaining_time":0.3833905479},
{"learn":[0.04495810304],"iteration":933,"passed_time":5.343364869,"remaining_time":0.3775825282},
{"learn":[0.04491213755],"iteration":934,"passed_time":5.347851758,"remaining_time":0.3717757907},
{"learn":[0.04484408741],"iteration":935,"passed_time":5.352538367,"remaining_time":0.3659855293},
{"learn":[0.04479199578],"iteration":936,"passed_time":5.357156379,"remaining_time":0.3601930116},
{"learn":[0.04470082291],"iteration":937,"passed_time":5.36177518,"remaining_time":0.3544030503},
{"learn":[0.04466811773],"iteration":938,"passed_time":5.366334076,"remaining_time":0.3486116918},
{"learn":[0.04462768309],"iteration":939,"passed_time":5.370943819,"remaining_time":0.3428262012},
{"learn":[0.04458798205],"iteration":940,"passed_time":5.375608119,"remaining_time":0.3370466302},
{"learn":[0.04455209869],"iteration":941,"passed_time":5.380061936,"remaining_time":0.3312564674},
{"learn":[0.04453333155],"iteration":942,"passed_time":5.384875538,"remaining_time":0.3254908862},
{"learn":[0.04447662648],"iteration":943,"passed_time":5.389320617,"remaining_time":0.3197054603},
{"learn":[0.04443076505],"iteration":944,"passed_time":5.393862454,"remaining_time":0.3139285026},
{"learn":[0.04439937744],"iteration":945,"passed_time":5.398377901,"remaining_time":0.3081526497},
{"learn":[0.04438956499],"iteration":946,"passed_time":5.402821062,"remaining_time":0.3023754132},
{"learn":[0.04429872887],"iteration":947,"passed_time":5.4072983,"remaining_time":0.2966028604},
{"learn":[0.04424518814],"iteration":948,"passed_time":5.411778107,"remaining_time":0.2908331754},
{"learn":[0.04416031961],"iteration":949,"passed_time":5.416553885,"remaining_time":0.2850817834},
{"learn":[0.0440640174],"iteration":950,"passed_time":5.421060047,"remaining_time":0.2793185513},
{"learn":[0.04403454485],"iteration":951,"passed_time":5.425502998,"remaining_time":0.273554773},
{"learn":[0.04397480195],"iteration":952,"passed_time":5.430147844,"remaining_time":0.2678037237},
{"learn":[0.04393199912],"iteration":953,"passed_time":5.435067958,"remaining_time":0.2620682663},
{"learn":[0.04390264732],"iteration":954,"passed_time":5.43953593,"remaining_time":0.2563132114},
{"learn":[0.04385117042],"iteration":955,"passed_time":5.443992848,"remaining_time":0.2505603403},
{"learn":[0.04379110332],"iteration":956,"passed_time":5.458833039,"remaining_time":0.2452767196},
{"learn":[0.04373442025],"iteration":957,"passed_time":5.471537982,"remaining_time":0.2398795357},
{"learn":[0.04367883582],"iteration":958,"passed_time":5.480578978,"remaining_time":0.2343104672},
{"learn":[0.04363666712],"iteration":959,"passed_time":5.490009926,"remaining_time":0.2287504136},
{"learn":[0.04360520677],"iteration":960,"passed_time":5.499219185,"remaining_time":0.2231733072},
{"learn":[0.04356774541],"iteration":961,"passed_time":5.508378515,"remaining_time":0.2175866773},
{"learn":[0.04348848418],"iteration":962,"passed_time":5.517396053,"remaining_time":0.2119871796},
{"learn":[0.04343036043],"iteration":963,"passed_time":5.524782825,"remaining_time":0.2063196906},
{"learn":[0.04337939331],"iteration":964,"passed_time":5.531708483,"remaining_time":0.2006319139},
{"learn":[0.04334892628],"iteration":965,"passed_time":5.538892391,"remaining_time":0.1949506639},
{"learn":[0.0432998955],"iteration":966,"passed_time":5.545941243,"remaining_time":0.189261697},
{"learn":[0.04327327143],"iteration":967,"passed_time":5.553166702,"remaining_time":0.1835757588},
{"learn":[0.04324510442],"iteration":968,"passed_time":5.560068799,"remaining_time":0.177876298},
{"learn":[0.04317020389],"iteration":969,"passed_time":5.567095875,"remaining_time":0.1721782229},
{"learn":[0.04310767474],"iteration":970,"passed_time":5.574452681,"remaining_time":0.1664872582},
{"learn":[0.04307103186],"iteration":971,"passed_time":5.581843575,"remaining_time":0.1607938479},
{"learn":[0.04304742323],"iteration":972,"passed_time":5.58887802,"remaining_time":0.1550870571},
{"learn":[0.04300768832],"iteration":973,"passed_time":5.595939197,"remaining_time":0.1493782537},
{"learn":[0.04296827571],"iteration":974,"passed_time":5.602980338,"remaining_time":0.1436661625},
{"learn":[0.04287972255],"iteration":975,"passed_time":5.608748972,"remaining_time":0.1379200567},
{"learn":[0.04281073864],"iteration":976,"passed_time":5.614029374,"remaining_time":0.132162411},
{"learn":[0.04276168258],"iteration":977,"passed_time":5.618698925,"remaining_time":0.1263920004},
{"learn":[0.042701586],"iteration":978,"passed_time":5.623521346,"remaining_time":0.1206271177},
{"learn":[0.04267805275],"iteration":979,"passed_time":5.628195925,"remaining_time":0.1148611413},
{"learn":[0.04264375048],"iteration":980,"passed_time":5.632927723,"remaining_time":0.1090984982},
{"learn":[0.04258255448],"iteration":981,"passed_time":5.637640343,"remaining_time":0.103337603},
{"learn":[0.04254194903],"iteration":982,"passed_time":5.643134356,"remaining_time":0.09759235406},
{"learn":[0.042482506],"iteration":983,"passed_time":5.647841956,"remaining_time":0.09183482856},
{"learn":[0.04244301781],"iteration":984,"passed_time":5.652506503,"remaining_time":0.08607877923},
{"learn":[0.0423613134],"iteration":985,"passed_time":5.657308371,"remaining_time":0.0803268937},
{"learn":[0.04230074682],"iteration":986,"passed_time":5.662077569,"remaining_time":0.07457650294},
{"learn":[0.04225336246],"iteration":987,"passed_time":5.666689538,"remaining_time":0.06882618872},
{"learn":[0.04216859483],"iteration":988,"passed_time":5.67150273,"remaining_time":0.06308041459},
{"learn":[0.04214206933],"iteration":989,"passed_time":5.67630271,"remaining_time":0.05733639101},
{"learn":[0.04206121644],"iteration":990,"passed_time":5.681075562,"remaining_time":0.0515940263},
{"learn":[0.04200663097],"iteration":991,"passed_time":5.685826542,"remaining_time":0.04585343986},
{"learn":[0.04199866754],"iteration":992,"passed_time":5.690554701,"remaining_time":0.0401146857},
{"learn":[0.04194553678],"iteration":993,"passed_time":5.69519874,"remaining_time":0.03437745718},
{"learn":[0.04184401592],"iteration":994,"passed_time":5.699998477,"remaining_time":0.02864320843},
{"learn":[0.04178188586],"iteration":995,"passed_time":5.704934278,"remaining_time":0.02291138264},
{"learn":[0.04171269244],"iteration":996,"passed_time":5.709649407,"remaining_time":0.01718048969},
{"learn":[0.04167414947],"iteration":997,"passed_time":5.714303422,"remaining_time":0.01145150986},
{"learn":[0.04164358631],"iteration":998,"passed_time":5.719743648,"remaining_time":0.005725469117},
{"learn":[0.0416013609],"iteration":999,"passed_time":5.728099673,"remaining_time":0}
]}